{"data":{"k_ele":[{"e":"恰も","p":true},{"e":"宛も"}],"r_ele":[{"r":"あたかも","p":true},{"r":"あだかも"}],"sense":[{"gloss":"as if, as it were, as though","pos":["adv"]},{"gloss":"right then, just then, at that moment","pos":["adv"]}],"m":["uk"]},"sdata":[{"j":"|あたかも|↑永遠↑↓えいえん↓を↑傷↑↓きず↓つけることがないかのごとく↑暇↑↓いとま↓をつぶしているが・・・。","e":"As if you could kill time without injuring eternity."},{"j":"↑大学↑↓だいがく↓↑時代↑↓じだい↓を↑振↑↓ふ↓り↑返↑↓かえ↓ってみると|あたかも|１↑世紀↑↓せいき↓↑前↑↓まえ↓の↑事↑↓こと↓のように↑思↑↓おも↓える。","e":"Looking back on our college days, it seems as if they were a century ago."},{"j":"そこに↑立↑↓た↓ったかれは|あたかも|↑悪鬼↑↓あっき↓のようだった。","e":"As he stood there he might have been a fiend."},{"j":"↑彼↑↓かれ↓は|あたかも|すべてを↑知↑↓し↓っているかのように↑話↑↓はな↓す。","e":"He talks as if he knew everything."},{"j":"↑彼↑↓かれ↓は|あたかも|↑金持↑↓かねも↓ちのような↑口↑↓くち↓の↑利↑↓き↓き↑方↑↓かた↓をする。","e":"He talks as if he were rich."},{"j":"↑彼↑↓かれ↓は|あたかも|↑病気↑↓びょうき↓であったかのような↑顔↑↓かお↓つきをしていた。","e":"He looked as if he had been ill."},{"j":"↑彼↑↓かれ↓は|あたかも|↑有名↑↓ゆうめい↓な↑政治↑↓せいじ↓↑家↑↓か↓であるかのようにふるまう。","e":"He behaves as if he were a famous statesman."},{"j":"↑彼↑↓かれ↓は|あたかも|すべてを↑知↑↓し↓っているかのように↑話↑↓はな↓す。","e":"He talks as though he knew everything."},{"j":"↑彼↑↓かれ↓らは|あたかも|↑蟻↑↓あり↓のように↑働↑↓はたら↓いた。","e":"They worked like so many ants."},{"j":"↑彼女↑↓かのじょ↓は|あたかも|↑幽霊↑↓ゆうれい↓でも↑見↑↓み↓たかのように↑見↑↓み↓えた。","e":"She looked as if she had seen a ghost."},{"j":"↑話↑↓はな↓し↑言葉↑↓ことば↓において、↑我々↑↓われわれ↓は↑言葉↑↓ことば↓の↑中↑↓なか↓に↑休止↑↓きゅうし↓を↑入↑↓い↓れないが、|あたかも|↑分↑↓わ↓けられた↑言葉↑↓ことば↓を↑聞↑↓き↓いているようにそれらを↑明確↑↓めいかく↓に↑理解↑↓りかい↓できることは、いくらか↑驚↑↓おどろ↓かされる↑事実↑↓じじつ↓である。","e":"In spoken language, we do not pause between words, a fact that is somewhat surprising. We seem to hear separate words; we can clearly make them out."}]}