{"data":{"k_ele":[{"e":"腕時計","p":true}],"r_ele":[{"r":"うでどけい","p":true}],"sense":[{"gloss":"wristwatch, watch","pos":["n"]}]},"sdata":[{"j":"↑机↑↓つくえ↓の↑上↑↓うえ↓の↑腕時計↑↓|うでどけい|↓は↑私↑↓わたし↓のです。","e":"The watch on the desk is mine."},{"j":"これは↑私↑↓わたし↓が↑失↑↓な↓くした↑腕時計↑↓|うでどけい|↓だ。","e":"This is the same watch that I've lost."},{"j":"この↑腕時計↑↓|うでどけい|↓は↑祖父↑↓そふ↓が↑私↑↓わたし↓に↑残↑↓のこ↓してくれたものだ。","e":"This watch was handed down to me by my grandfather."},{"j":"この↑腕時計↑↓|うでどけい|↓は↑新型↑↓しんがた↓です。","e":"This watch is a new type."},{"j":"この↑腕時計↑↓|うでどけい|↓はいくらですか。","e":"How much is this watch?"},{"j":"この↑腕時計↑↓|うでどけい|↓は↑５↑↓ご↓↑万↑↓まん↓↑円↑↓えん↓くらいする。","e":"This watch costs around fifty thousand yen."},{"j":"この↑腕時計↑↓|うでどけい|↓は７↑万↑↓まん↓↑円↑↓えん↓もしました。","e":"This watch cost 70,000 yen."},{"j":"あの↑腕時計↑↓|うでどけい|↓はどうしたの。","e":"What have you done with that wristwatch?"},{"j":"あなたは↑腕時計↑↓|うでどけい|↓を↑持↑↓も↓っています。","e":"You have a watch."},{"j":"↑私↑↓わたし↓の↑腕時計↑↓|うでどけい|↓は↑日↑↓ひ↓に↑３↑↓さん↓↑分↑↓ぷん↓↑遅↑↓おく↓れる。","e":"My watch loses three minutes a day."},{"j":"↑私↑↓わたし↓の↑腕時計↑↓|うでどけい|↓は↑１０分↑↓じゅっぷん↓も↑進↑↓すす↓んでいる。","e":"My watch is ten minutes fast."},{"j":"↑私↑↓わたし↓の↑腕時計↑↓|うでどけい|↓は↑少↑↓すこ↓し↑進↑↓すす↓む。","e":"My watch runs too fast."},{"j":"↑私↑↓わたし↓の↑腕時計↑↓|うでどけい|↓は↑正確↑↓せいかく↓だ。","e":"My wristwatch keeps good time."},{"j":"↑私↑↓わたし↓はいつも↑腕時計↑↓|うでどけい|↓を↑持↑↓も↓っているので↑時間↑↓じかん↓が↑分↑↓わ↓かります。","e":"I always wear a watch so I know what time it is."},{"j":"↑私↑↓わたし↓は↑腕時計↑↓|うでどけい|↓を↑買↑↓か↓った。","e":"I bought a watch."},{"j":"↑腕時計↑↓|うでどけい|↓を↑買↑↓か↓って、↑次↑↓つぎ↓の↑日↑↓ひ↓になくしてしまった。","e":"I bought a watch and I lost it the next day."},{"j":"↑私↑↓わたし↓は↑息子↑↓むすこ↓に↑腕時計↑↓|うでどけい|↓を↑買↑↓か↓ってやるつもりです。","e":"I'll buy a watch for my son."},{"j":"↑息子↑↓むすこ↓には↑腕時計↑↓|うでどけい|↓を↑買↑↓か↓ってあげるつもりです。","e":"I'll buy a watch for my son."},{"j":"↑私↑↓わたし↓は↑彼↑↓かれ↓に↑金↑↓きん↓の↑腕時計↑↓|うでどけい|↓を↑贈↑↓おく↓った。","e":"I presented him with a gold watch."},{"j":"↑私↑↓わたし↓は↑彼女↑↓かのじょ↓に↑素敵↑↓すてき↓な↑腕時計↑↓|うでどけい|↓を↑買↑↓か↓ってあげた。","e":"I bought a wonderful watch for her."},{"j":"↑私↑↓わたし↓は↑彼女↑↓かのじょ↓に↑腕時計↑↓|うでどけい|↓を↑買↑↓か↓って↑上↑↓あ↓げた。","e":"I got her a wrist watch."},{"j":"↑私↑↓わたし↓は↑腕時計↑↓|うでどけい|↓を↑修理↑↓しゅうり↓してもらわなければならない。","e":"I must have my watch repaired."},{"j":"↑先日↑↓せんじつ↓↑腕時計↑↓|うでどけい|↓を↑買↑↓か↓った。↑時間↑↓じかん↓が↑正確↑↓せいかく↓だ。","e":"I bought a watch the other day. It keeps good time."},{"j":"↑誰↑↓だれ↓かが↑君↑↓きみ↓の↑腕時計↑↓|うでどけい|↓を↑盗↑↓ぬす↓んだにちがいない。","e":"Someone must've stolen your watch."},{"j":"↑彼↑↓かれ↓の↑身元↑↓みもと↓は↑腕時計↑↓|うでどけい|↓で↑確認↑↓かくにん↓できた。","e":"They were able to identify him by his wrist watch."},{"j":"↑彼↑↓かれ↓は↑腕時計↑↓|うでどけい|↓をちらっと↑見↑↓み↓た。","e":"He glanced at his watch."},{"j":"↑彼↑↓かれ↓はとても↑高価↑↓こうか↓な↑腕時計↑↓|うでどけい|↓を↑持↑↓も↓っている。","e":"He has a very expensive watch."},{"j":"↑彼↑↓かれ↓は↑時折↑↓ときおり↓↑腕時計↑↓|うでどけい|↓をちらりと↑見↑↓み↓た。","e":"He glanced at his wristwatch now and then."},{"j":"↑彼↑↓かれ↓は↑腕時計↑↓|うでどけい|↓を↑見↑↓み↓た。","e":"He looked at his watch."},{"j":"↑彼女↑↓かのじょ↓は↑素敵↑↓すてき↓な↑腕時計↑↓|うでどけい|↓をしている。","e":"She is wearing a nice watch."},{"j":"↑腕時計↑↓|うでどけい|↓が↑見↑↓み↓つからないんです。","e":"I can't find my watch."},{"j":"↑犬↑↓いぬ↓が↑腕時計↑↓|うでどけい|↓と↑扇子↑↓せんす↓を↑食↑↓く↓った。","e":"The dog ate a watch and a Japanese fan."},{"j":"↑腕時計↑↓|うでどけい|↓の↑収集↑↓しゅうしゅう↓が↑趣味↑↓しゅみ↓だ。","e":"The collection of wristwatches is a hobby."},{"j":"↑腕時計↑↓|うでどけい|↓はどこにも↑見↑↓み↓つからなかった。","e":"The watch was not to be found anywhere."},{"j":"↑私↑↓わたし↓は↑彼女↑↓かのじょ↓に↑腕時計↑↓|うでどけい|↓を↑買↑↓か↓って↑上↑↓あ↓げた。","e":"I bought her a watch."},{"j":"これは↑私↑↓わたし↓が↑失↑↓な↓くした↑腕時計↑↓|うでどけい|↓だ。","e":"This is the watch that I'd lost."},{"j":"トムは↑腕時計↑↓|うでどけい|↓を↑見↑↓み↓た。","e":"Tom looked at his watch."},{"j":"トムは↑腕時計↑↓|うでどけい|↓の↑時間↑↓じかん↓を↑確↑↓たし↓かめた。","e":"Tom checked his watch."},{"j":"↑私↑↓わたし↓の↑腕時計↑↓|うでどけい|↓は↑少↑↓すこ↓し↑進↑↓すす↓む。","e":"My wristwatch is running a bit too fast."},{"j":"↑腕時計↑↓|うでどけい|↓、2↑分↑↓ふん↓↑早↑↓はや↓くセットしなきゃ。","e":"I need to set my watch to two minutes faster."}]}