{"data":{"k_ele":[{"e":"叶う","p":true},{"e":"適う"},{"e":"敵う"}],"r_ele":[{"r":"かなう","p":true}],"sense":[{"gloss":"to come true (of a wish, prayer, etc.), to be realized, to be fulfilled","pos":["v5u"]},{"gloss":"to suit (e.g. a purpose), to meet (wishes, ideals, etc.), to conform to (standards, rules, etc.), to be consistent with","pos":["v5u"],"x":["道理に適う"]},{"gloss":"to match (implies competition), to rival, to bear (e.g. the heat)","pos":["v5u"]}]},"sdata":[{"j":"↑誰↑↓だれ↓しも、↑夢↑↓ゆめ↓は|かなう|と↑信↑↓しん↓じたいものだ。","e":"Everyone would like to believe that dreams can come true."},{"j":"↑願↑↓ねが↓っただけで↑望↑↓のぞ↓みが|かなう|なら↑貧乏人↑↓びんぼうにん↓も↑金持↑↓かねも↓ちになれようが。","e":"If wishes were horses, beggars might ride."},{"j":"↑穏↑↓おだ↓や|かな↑海↑↓う|み↓にヨットが↑二↑↓に↓↑三↑↓さん↓↑浮↑↓う↓かんでいる。","e":"There are a few yachts on the calm sea."},{"j":"こと↑英単語↑↓えいたんご↓の↑暗記↑↓あんき↓にかけては、↑彼↑↓かれ↓に|かなう|↑者↑↓もの↓はいない。","e":"When it comes to learning English words by heart, nobody can beat him."},{"j":"↑英語↑↓えいご↓で↑彼↑↓かれ↓に|かなう|↑者↑↓もの↓はいない。","e":"No one can match him in English."},{"j":"もし↑病気↑↓びょうき↓の↑人↑↓ひと↓が↑千↑↓せん↓↑羽↑↓わ↓の↑鶴↑↓づる↓を↑折↑↓お↓ると、その↑人↑↓ひと↓の↑願↑↓ねが↓いが↑叶↑↓|かな↓う|の。","e":"If a sick person folds one thousand paper cranes, her wish will come true."},{"j":"もしも↑叶↑↓|かな↓う|なら、↑私↑↓わたし↓は↑失↑↓うしな↓った↑時間↑↓じかん↓の↑埋↑↓う↓め↑合↑↓あ↓わせをしたい。","e":"If I could have a wish, I'd wish I could make up for lost time."},{"j":"バレエ↑音楽↑↓おんがく↓の↑指揮↑↓しき↓↑者↑↓しゃ↓として↑彼↑↓かれ↓に|かなう|ものはいない。","e":"He stands alone as a conductor of ballet music."},{"j":"テニスでは↑彼↑↓かれ↓に|かなう|ものはいない。","e":"No one can match him at tennis."},{"j":"そいつは↑真↑↓ま↓っ↑赤↑↓|か↓なう|そだ。","e":"That's a blessed lie."}]}