{"data":{"k_ele":[{"e":"頭","p":true}],"r_ele":[{"r":"あたま","p":true},{"r":"かしら","p":true}],"sense":[{"gloss":"head","pos":["n"]},{"gloss":"hair (on one's head)","pos":["n"]},{"gloss":"mind, brains, intellect","pos":["n"]},{"gloss":"leader, chief, boss, captain","pos":["n"]},{"gloss":"top, tip","pos":["n"]},{"gloss":"beginning, start","pos":["n"]},{"gloss":"head, person","pos":["n"],"x":["頭数"]},{"gloss":"down payment, deposit","pos":["n"],"m":["abbr"],"x":["頭金"]},{"gloss":"top structural component of a kanji","pos":["n"]},{"gloss":"pair","pos":["n"],"f":["mahj"],"m":["col"],"x":["雀頭・ジャントー"]}]},"sdata":[{"j":"その↑答↑↓こた↓えを↑知↑↓し↓るのにあなたは↑本当↑↓ほんとう↓にその↑質問↑↓しつもん↓をする↑必要↑↓ひつよう↓があるの|かしら|。","e":"Do you really need to ask the question to know the answer?"},{"j":"どれくらいかかるの|かしら|。","e":"I wonder how long it's going to take."},{"j":"あなた↑私↑↓わたし↓が↑誰↑↓だれ↓|か↑知↑↓し↓ら|ないのね。","e":"You don't know who I am."},{"j":"↑君↑↓きみ↓は↑何↑↓なに↓が↑欲↑↓ほ↓しいの|か↑知↑↓し↓ら|せてください。","e":"Please let me know what you want."},{"j":"↑君↑↓きみ↓は↑何↑↓なに↓か↑書↑↓か↓くものを↑持↑↓も↓っている|かしら|。","e":"I wonder if you have something to write with."},{"j":"↑私↑↓わたし↓たちは↑学↑↓まね↓べば↑学↑↓まな↓ぶほどいかに↑少↑↓すくな↓しし|か↑知↑↓し↓ら|ないかがわかる。","e":"The more we learn, the more we realize how little we know."},{"j":"↑学↑↓まね↓べば↑学↑↓まな↓ぶほど、いかに↑少↑↓すくな↓しし|か↑知↑↓し↓ら|ないかがわかってくる。","e":"The more we learn, the more we realize how little we know."},{"j":"↑家↑↓いえ↓の↑回↑↓まわ↓りには↑何↑↓なに↓|かしら|いつも↑仕事↑↓しごと↓がある。","e":"There are always some chores to be done about the house."},{"j":"↑何↑↓なん↓↑年↑↓ねん↓もたっているので↑彼女↑↓かのじょ↓は↑私↑↓わたし↓のことを↑見分↑↓みわ↓けがつく|かしら|。","e":"I wonder if she will recognize me after all those years."},{"j":"↑何↑↓なに↓をやってみせてくれるの|かしら|？","e":"I wonder what they have in store for us under the big top?"}]}