{"data":{"k_ele":[{"e":"教育委員会","p":true}],"r_ele":[{"r":"きょういくいいんかい","p":true}],"sense":[{"gloss":"Board of Education","pos":["n"]}]},"sdata":[{"j":"↑教育↑↓|きょういく↓↑委員↑↓いいん↓↑会↑↓かい|↓↑委員↑↓いいん↓↑長↑↓ちょう↓に↑動議↑↓どうぎ↓の↑確認↑↓かくにん↓を↑願↑↓ねが↓います。","e":"And I call on the chairman of the Education Committee to support the motion."},{"j":"↑教育↑↓|きょういく↓↑委員↑↓いいん↓↑会↑↓かい|↓は↑何↑↓なに↓としてでもあの↑本↑↓ほん↓を↑発売↑↓はつばい↓↑禁止↑↓きんし↓にするでしょう。","e":"The local school board would go to any length to ban that book."},{"j":"↑教育↑↓|きょういく↓↑委員↑↓いいん↓↑会↑↓かい|↓が↑学校↑↓がっこう↓を↑管理↑↓かんり↓している。","e":"The Board of Education governs the schools."},{"j":"↑最初↑↓さいしょ↓の↑議題↑↓ぎだい↓は、↑教育↑↓|きょういく↓↑委員↑↓いいん↓↑会↑↓かい|↓によって↑提出↑↓ていしゅつ↓された↑動議↑↓どうぎ↓です。","e":"The first item is a motion proposed by the Education Committee."},{"j":"↑州↑↓しゅう↓↑教育↑↓|きょういく↓↑委員↑↓いいん↓↑会↑↓かい|↓はある↑学校↑↓がっこう↓を↑閉校↑↓へいこう↓したいと↑思↑↓おも↓っていますが、その↑考↑↓かんが↓えに↑同意↑↓どうい↓しない↑人々↑↓ひとびと↓もいます。","e":"The Council Education Committee wants to close a school, but some people don't agree with the idea."}]}