{"data":{"k_ele":[{"e":"結構","p":true}],"r_ele":[{"r":"けっこう","p":true}],"sense":[{"gloss":"splendid, nice, wonderful, delightful, lovely, excellent, fine","pos":["adj-na"]},{"gloss":"sufficient, satisfactory, enough, fine, all right, OK","pos":["adj-na"]},{"gloss":"not needing (any more of something), (already) having enough, fine (as in \"I'm fine\"), no, thank you","pos":["adj-na"]},{"gloss":"rather, quite, fairly, pretty, surprisingly, quite a bit, fairly well","pos":["adv"]},{"gloss":"structure, construction, framework, architecture","pos":["n"]}]},"sdata":[{"j":"↑頑固↑↓がんこ↓↑一↑↓いち↓↑徹↑↓てっ↓のボスだと↑思↑↓おも↓っていたけれど、↑結構↑↓|けっこう|↓かわいいところもあるじゃない。","e":"I thought our boss was stubborn as a mule but actually he has his cute side."},{"j":"↑私↑↓わたし↓たちのフライトが↑欠航↑↓|けっこう|↓になりました。","e":"Our flight was canceled."},{"j":"↑何↑↓なん↓でも|けっこう|です。","e":"Anything will do."},{"j":"↑一↑↓いち↓↑日↑↓にち↓↑中↑↓じゅう↓コンピューターに↑向↑↓む↓かってるから、↑結構↑↓|けっこう|↓↑電磁波↑↓でんじは↓↑浴↑↓あ↓びてる。","e":"I sit in front of a computer screen all day, so I get pretty heavily bombarded by electro-magnetic waves."},{"j":"↑以下↑↓いか↓の↑空欄↑↓くうらん↓↑部分↑↓ぶぶん↓にご↑記入↑↓きにゅう↓↑頂↑↓いただ↓くだけで↑結構↑↓|けっこう|↓です。","e":"All you have to do is fill in the blanks below."},{"j":"わざわざ↑電話↑↓でんわ↓をかけてくださらなくて|けっこう|です。","e":"Don't bother to call me."},{"j":"わざわざおいでにならなくて↑結構↑↓|けっこう|↓です。","e":"Don't bother to come to my house."},{"j":"いえ、↑結構↑↓|けっこう|↓です。","e":"No, thank you."},{"j":"それで↑結構↑↓|けっこう|↓です。","e":"That will do."},{"j":"もう↑結構↑↓|けっこう|↓です。","e":"I don't want any more."}]}