{"data":{"k_ele":[{"e":"凍る","p":true},{"e":"氷る","i":["rK"]}],"r_ele":[{"r":"こおる","p":true}],"sense":[{"gloss":"to freeze, to become frozen, to freeze over","pos":["v5r","vi"]}]},"sdata":[{"j":"↑来週↑↓らいしゅう↓には↑凍↑↓|こお↓る|かも↑知↑↓し↓れない。","e":"It may freeze next week."},{"j":"その↑光景↑↓こうけい↓を↑見↑↓み↓て↑血↑↓ち↓の↑凍↑↓|こお↓る|↑思↑↓おも↓いがした。","e":"My blood curdled at that sight."},{"j":"そのニュースをラジオで↑聴↑↓き↓いたとき↑背筋↑↓せすじ↓の↑凍↑↓|こお↓る|↑思↑↓おも↓いがした。","e":"When I heard the news on the radio, a chill ran down my spine."},{"j":"↑支払↑↓しはら↓いを↑滞↑↓とど|こお↓る|↑原因↑↓げんいん↓となるような↑問題↑↓もんだい↓があるのですが。","e":"I have run into a problem that is causing the delay of my payment."},{"j":"↑凍↑↓|こお↓る|ように↑冷↑↓つめ↓たい。","e":"It is freezing cold."},{"j":"↑水↑↓みず↓は↑摂氏↑↓せっし↓↑０↑↓れい↓↑度↑↓ど↓で↑凍↑↓|こお↓る|。","e":"Water freezes at 0 degrees Centigrade."},{"j":"↑水↑↓みず↓は↑華氏↑↓かし↓３２↑度↑↓ど↓で↑凍↑↓|こお↓る|。","e":"Water freezes at 32 degrees Fahrenheit."},{"j":"↑水↑↓みず↓は３２↑度↑↓ど↓↑Ｆ↑↓えふ↓で↑凍↑↓|こお↓る|。","e":"Water freezes at 32 degrees Fahrenheit."},{"j":"↑水↑↓みず↓は↑液体↑↓えきたい↓である。↑凍↑↓|こお↓る|と↑固体↑↓こたい↓になる。","e":"Water is liquid. When it freezes, it becomes solid."},{"j":"↑水↑↓みず↓は↑凍↑↓|こお↓る|と↑固体↑↓こたい↓になる。","e":"Water becomes solid when it freezes."},{"j":"↑冬↑↓ふゆ↓は↑道路↑↓どうろ↓が↑凍↑↓|こお↓る|のでお↑年寄↑↓としよ↓りがよく↑転↑↓ころ↓びます。","e":"In the winter, many older people slip on ice and fall down."},{"j":"↑凍↑↓|こお↓る|ような↑冷↑↓つめ↓たい↑風↑↓かぜ↓が↑骨↑↓ほね↓までしみた。","e":"An icy blast of wind cut me to the bone."},{"j":"↑水↑↓みず↓は↑液体↑↓えきたい↓である。↑凍↑↓|こお↓る|と↑固体↑↓こたい↓になる。","e":"Water is liquid. It becomes solid when it freezes."},{"j":"↑水↑↓みず↓は↑摂氏↑↓せっし↓↑０↑↓れい↓↑度↑↓ど↓で↑凍↑↓|こお↓る|。","e":"Water freezes at 0°C."},{"j":"↑水↑↓みず↓は↑摂氏↑↓せっし↓↑０↑↓れい↓↑度↑↓ど↓で↑凍↑↓|こお↓る|。","e":"Water freezes at zero degrees Celsius."},{"j":"↑水↑↓みず↓は↑零↑↓れい↓↑度↑↓ど↓で↑凍↑↓|こお↓る|んだよね？","e":"Water freezes at zero Celsius, right?"}]}