{"data":{"k_ele":[{"e":"固化","p":true}],"r_ele":[{"r":"こか","p":true}],"sense":[{"gloss":"solidification","pos":["n","vs","vi"]}]},"sdata":[{"j":"それがど|こか|ら↑来↑↓き↓たのか↑分↑↓わ↓からなかった。","e":"I didn't know where it came from."},{"j":"こ|こか|ら↑遠↑↓とお↓くまで↑行↑↓い↓けるボートが↑欲↑↓ほ↓しいです。","e":"I want a boat that will take me far away from here."},{"j":"「↑以前↑↓いぜん↓にど|こか|で↑会↑↓あ↓ったことがありませんか」とその↑学生↑↓がくせい↓はたずねた。","e":"Haven't we met somewhere before? asked the student."},{"j":"こ|こか|ら↑遠↑↓とお↓いの？","e":"Is it far from here?"},{"j":"↑君↑↓きみ↓は↑大↑↓おお↓きい↑箱↑↓は|こ↓か|↑小↑↓ちい↓さい↑箱↑↓はこ↓のどちらかをとっていいよ。","e":"You may take either the big box or the small one."},{"j":"↑君↑↓きみ↓はこ|こか|ら↑東京↑↓とうきょう↓まで↑車↑↓くるま↓で↑行↑↓い↓くのにどのくらい↑時間↑↓じかん↓がかかりましたか。","e":"How long did it take you to drive from here to Tokyo?"},{"j":"↑君↑↓きみ↓はこ|こか|らすぐに↑逃↑↓に↓げたほうがよい。","e":"You had better get away from here at once."},{"j":"あなたは↑何処↑↓ど|こ↓か|ら↑来↑↓き↓ましたか。","e":"Where do you come from?"},{"j":"↑空港↑↓くうこう↓までいくバスは、ど|こか|らでますか。","e":"Where does the airport bus leave from?"},{"j":"↑空港↑↓くうこう↓バスはど|こか|ら↑出↑↓で↓ますか。","e":"Where can I get the airport bus?"},{"j":"↑強盗↑↓ごうとう↓↑達↑↓たち↓が↑木陰↑↓|こか|げ↓から↑出↑↓で↓てきて↑彼↑↓かれ↓に↑襲↑↓おそ↓い↑掛↑↓か↓かった。","e":"The robbers fell upon him from behind the trees."},{"j":"↑奇跡↑↓きせき↓でも↑起↑↓お↓こらない↑限↑↓かぎ↓り、↑彼↑↓かれ↓はそ|こか|ら↑逃↑↓に↓げられないんじゃないか。","e":"He won't be able to escape from there without a miracle, will he?"},{"j":"↑学校↑↓がっこう↓はこ|こか|ら↑歩↑↓ある↓いて↑５↑↓ご↓↑分↑↓ふん↓です。","e":"The school is only five minutes' walk from here."},{"j":"↑確↑↓たし↓かにど|こか|であった↑人↑↓ひと↓だが、↑誰↑↓だれ↓だか↑思↑↓おも↓い↑出↑↓だ↓せない。","e":"I am sure I met him somewhere, but I do not remember who he is."},{"j":"たしかにど|こか|で↑会↑↓あ↓った↑人↑↓ひと↓だが、だれだか↑思↑↓おも↓い↑出↑↓だ↓せない。","e":"I am sure I met him somewhere, but I do not remember who he is."},{"j":"↑外国↑↓がいこく↓にいる↑息子↑↓むす|こ↓か|ら↑便↑↓たよ↓りがない。","e":"I haven't heard from my son who is overseas."},{"j":"↑我々↑↓われわれ↓はそ|こか|ら↑推測↑↓すいそく↓できることがわかり↑始↑↓はじ↓めた。","e":"We began to see what we can deduce from it."},{"j":"↑私↑↓わたし↓たちのクラスは５０↑人↑↓にん↓の↑男↑↓おとこ↓の↑子↑↓|こ↓か|ら↑成↑↓な↓り↑立↑↓た↓っている。","e":"Our class consists of fifty boys."},{"j":"↑我々↑↓われわれ↓がこ|こか|ら↑駅↑↓えき↓まで↑歩↑↓ある↓いていくのに３０↑分↑↓ふん↓かかる。","e":"It takes us thirty minutes to walk from here to the station."},{"j":"↑夏休↑↓なつやす↓みも↑近↑↓ちか↓いけど、ど|こか|いいところ↑思↑↓おも↓い↑当↑↓あ↓たりますか。","e":"Summer vacation is near. Can you think of a good place for the holidays?"},{"j":"↑夏休↑↓なつやす↓みはど|こか|へ↑行↑↓い↓きましたか。","e":"Did you go anywhere during the summer vacation?"},{"j":"↑夏休↑↓なつやす↓みにど|こか|へ↑行↑↓い↓きましたか。","e":"Did you go anywhere during the summer vacation?"},{"j":"↑夏↑↓なつ↓にど|こか|↑行↑↓い↓きましたか。","e":"Did you go anywhere for the summer?"},{"j":"↑何↑↓なに↓とかそ|こか|ら↑脱出↑↓だっしゅつ↓した。","e":"We made it out of there."},{"j":"↑俺↑↓おれ↓、ペーパードライバーだから↑運転↑↓うんてん↓には↑自信↑↓じしん↓ないんだ。↑電車↑↓でんしゃ↓でど|こか|に↑行↑↓い↓こうよ。","e":"I'd rather go by train. I have a license, but no real driving experience, so I'm not very sure of myself behind the wheel."},{"j":"↑横↑↓よ|こ↓か|ら↑口↑↓くち↓を↑差↑↓さ↓しはさむな。","e":"Don't cut in with your remarks."},{"j":"↑駅↑↓えき↓はこ|こか|ら↑約↑↓やく↓３マイルのところに↑在↑↓あ↓ります。","e":"The station is about three miles from here."},{"j":"↑駅↑↓えき↓はこ|こか|ら↑車↑↓くるま↓で↑10分↑↓じゅっぷん↓です。","e":"The station is a ten minute drive from here."},{"j":"↑駅↑↓えき↓はこ|こか|ら↑近↑↓ちか↓いから、↑列車↑↓れっしゃ↓に↑間↑↓ま↓に↑合↑↓あ↓うだろう。","e":"The station is near here. You'll be in time for the train."},{"j":"↑駅↑↓えき↓はこ|こか|ら↑遠↑↓とお↓くない。","e":"The station is not far from here."},{"j":"↑一↑↓いち↓↑度↑↓ど↓にあまりたくさんのことに↑手↑↓て↓を↑出↑↓だ↓すと、ど|こか|ら↑始↑↓はじ↓めてよいか、わからないものだ。","e":"When one has too many irons in the fire, he doesn't know where to start working."},{"j":"↑一↑↓ひと↓↑人↑↓り↓の↑老人↑↓ろうじん↓が↑木陰↑↓|こか|げ↓で↑休↑↓やす↓んでいた。","e":"An old man was at rest under the tree."},{"j":"↑一見↑↓いっけん↓して、↑父↑↓ちち↓のど|こか|↑具合↑↓ぐあい↓が↑悪↑↓わる↓いことがわかった。","e":"I saw at a glance that there was something the matter with my father."},{"j":"↑医者↑↓いしゃ↓が↑勧↑↓すす↓めるので、ど|こか|へ↑転地↑↓てんち↓↑療養↑↓りょうよう↓に↑行↑↓い↓こうと↑思↑↓おも↓っています。","e":"I'm thinking of going somewhere for a change of air, since my doctor advises me to."},{"j":"いったん↑悪↑↓わる↓い↑習慣↑↓しゅうかん↓が↑身↑↓み↓につくと、そ|こか|ら↑抜↑↓ぬ↓け↑出↑↓だ↓すのは↑難↑↓むずか↓しいかもしれないよ。","e":"Once you've got into a bad habit, it can be difficult to get out of it."},{"j":"わたしの↑家↑↓いえ↓はこ|こか|らたった１マイルの↑所↑↓ところ↓にある。","e":"My house is only a mile from here."},{"j":"ライターをど|こか|に↑置↑↓お↓き↑忘↑↓わす↓れて↑見↑↓み↓つからない。","e":"I put my lighter down somewhere and now I can't find it."},{"j":"ライオンと↑虎↑↓とら↓は↑猫↑↓ね|こ↓↑科↑↓か|↓の↑２↑↓ふた↓つの↑違↑↓ちが↓った↑種↑↓しゅ↓である。","e":"The lion and the tiger are two different species of cat."},{"j":"もしかして、こ|こか|ら↑町↑↓まち↓へ↑行↑↓い↓く↑道↑↓みち↓をご↑存↑↓ぞん↓じではないでしょうか。","e":"Do you happen to know how to get downtown from here?"},{"j":"もうすぐこ|こか|ら↑逃↑↓に↓げ↑出↑↓だ↓すのだ。","e":"We're getting out of here in a moment."}]}