{"data":{"k_ele":[{"e":"指し手","p":true}],"r_ele":[{"r":"さして","p":true}],"sense":[{"gloss":"move (in shogi, chess, etc.)","pos":["n"]}]},"sdata":[{"j":"↑級友↑↓きゅうゆう↓を↑代表↑↓だいひょう↓してお↑礼↑↓れい↓の↑言葉↑↓ことば↓を↑述↑↓の↓べ|さして|いただきます。","e":"On behalf of my classmates, let me say a few words of thanks to you."},{"j":"↑帰国↑↓きこく↓↑後↑↓ご↓その↑問題↑↓もんだい↓を↑調査↑↓ちょう|さ↓して|みるつもりだ。","e":"I will inquire about the matter after I return home."},{"j":"↑温度↑↓おんど↓↑計↑↓けい↓は１０↑度↑↓ど↓を↑指↑↓|さ↓して|いる。","e":"The thermometer reads 10C."},{"j":"↑一瞬↑↓いっしゅん↓↑魔↑↓ま↓が↑差↑↓|さ↓して|↑盗↑↓ぬす↓んでしまった。","e":"I must have stolen it when I lost control of myself momentarily."},{"j":"マイクは↑先週↑↓せんしゅう↓↑歯↑↓ぱ↓を↑検査↑↓けん|さ↓して|もらった。","e":"Mike had his teeth checked last week."},{"j":"ブルータスがシーザーを↑刺↑↓|さ↓して|、シーザーが↑倒↑↓たお↓れる。","e":"Brutus stabs Caesar, and Caesar falls."},{"j":"なぜならば、↑精密↑↓せいみつ↓に↑検査↑↓けん|さ↓して|も↑何↑↓なに↓か↑欠点↑↓けってん↓が↑現↑↓あらわ↓れないほど↑美↑↓うつく↓しいものは↑存在↑↓そんざい↓しないからである。","e":"For nothing is so beautiful but that it betrays some defect on close inspection."},{"j":"その↑棒↑↓ぼう↓は↑交差↑↓こう|さ↓して|おかれた。","e":"The sticks were laid across each other."},{"j":"その↑博物館↑↓はくぶつかん↓は↑今↑↓いま↓は↑閉鎖↑↓へい|さ↓して|いる。","e":"The museum is closed now."},{"j":"その↑通↑↓とお↓りは↑十↑↓じゅう↓↑時↑↓じ↓を↑過↑↓す↓ぎると↑閉鎖↑↓へい|さ↓して|いた。","e":"The street was deserted after ten."}]}