{"data":{"k_ele":[{"e":"最大","p":true}],"r_ele":[{"r":"さいだい","p":true}],"sense":[{"gloss":"biggest, greatest, largest, maximum","pos":["n","adj-no"],"ant":["最小"]}]},"sdata":[{"j":"あなたにとってひらめきの↑最大↑↓|さいだい|↓の↑源↑↓みなもと↓は↑何↑↓なに↓？","e":"What is your greatest source of inspiration?"},{"j":"↑空腹↑↓くうふく↓は↑最大↑↓|さいだい|↓の↑社会↑↓しゃかい↓↑的↑↓てき↓↑不幸↑↓ふこう↓の↑一↑↓ひと↓つである。","e":"Hunger is one of the greatest social miseries."},{"j":"↑休暇↑↓きゅうか↓は↑短↑↓みじか↓いので、↑最大限↑↓|さいだい|げん↓に↑活用↑↓かつよう↓しなければなりません。","e":"We must make the most of our vacation, as it is so short."},{"j":"↑技術↑↓ぎじゅつ↓↑者↑↓しゃ↓の↑不足↑↓ふそく↓が↑当社↑↓とうしゃ↓の↑発展↑↓はってん↓の↑最大↑↓|さいだい|↓のネックだ。","e":"The shortage of engineers is the greatest bottleneck to the development of our company."},{"j":"↑技術↑↓ぎじゅつ↓↑革新↑↓かくしん↓のおかげで、その↑工場↑↓こうじょう↓の↑最大↑↓|さいだい|↓↑生産↑↓せいさん↓↑量↑↓りょう↓は２↑倍↑↓ばい↓になった。","e":"Thanks to the technological innovation, the maximum output of the factory has doubled."},{"j":"↑飢↑↓う↓えは↑最大↑↓|さいだい|↓の↑社会↑↓しゃかい↓↑的↑↓てき↓↑不幸↑↓ふこう↓の↑１↑↓ひと↓つである。","e":"Hunger is one of the strongest griefs."},{"j":"↑機会↑↓きかい↓は↑常↑↓つね↓に↑最大限↑↓|さいだい|げん↓に↑活用↑↓かつよう↓すべきだ。","e":"One should always make the most of one's opportunities."},{"j":"↑寛大↑↓かんだい↓すぎることが↑彼↑↓かれ↓の↑最大↑↓|さいだい|↓の↑欠点↑↓けってん↓です。","e":"It's his greatest fault to be too generous."},{"j":"↑会話↑↓かいわ↓は↑人生↑↓じんせい↓↑最大↑↓|さいだい|↓の↑喜↑↓よろこ↓びの↑一↑↓ひと↓つであることをご↑存知↑↓ぞんじ↓か。","e":"Do you know that conversation is one of the greatest pleasures in life?"},{"j":"↑我々↑↓われわれ↓は↑太陽↑↓たいよう↓エネルギーを↑最大限↑↓|さいだい|げん↓に↑活用↑↓かつよう↓しなければならない。","e":"We must make the best use of solar energy."},{"j":"↑貨幣↑↓かへい↓が、↑人類↑↓じんるい↓↑最大↑↓|さいだい|↓の↑発明↑↓はつめい↓↑品↑↓ひん↓のひとつだとこれまで↑呼↑↓よ↓ばれてきたのにも、↑十分↑↓じゅうぶん↓な↑理由↑↓りゆう↓がある。","e":"It is without justification that money has been called one of the greatest inventions of man."},{"j":"↑火↑↓ひ↓の↑利用↑↓りよう↓が↑人類↑↓じんるい↓の↑最大↑↓|さいだい|↓の↑発明↑↓はつめい↓と↑考↑↓かんが↓えてもよいでしょう。","e":"Making use of fire may be regarded as man's greatest invention."},{"j":"↑何↑↓なに↓をするにも↑最大限↑↓|さいだい|げん↓の↑努力↑↓どりょく↓をすべきだ。","e":"You should make as much effort as possible in whatever you do."},{"j":"↑横浜↑↓よこはま↓は↑日本↑↓にっぽん↓で↑最大↑↓|さいだい|↓の↑都市↑↓とし↓の↑一↑↓ひと↓つだ。","e":"Yokohama is one of the largest cities in Japan."},{"j":"↑悪↑↓わる↓い↑状況↑↓じょうきょう↓を↑最大限↑↓|さいだい|げん↓に↑生↑↓い↓かすようにするべきだ。","e":"You should make the best of a bad situation."},{"j":"↑愛↑↓いと↓し↑愛↑↓あい↓されるということは↑最大↑↓|さいだい|↓の↑幸福↑↓こうふく↓だ。","e":"To love and to be loved is the greatest happiness."},{"j":"われわれは↑現在↑↓げんざい↓のわれわれを↑最大限↑↓|さいだい|げん↓にいかさなければならない。","e":"We must make the best of what we are."},{"j":"ロンドンは↑世界↑↓せかい↓↑最大↑↓|さいだい|↓の↑都市↑↓とし↓のひとつである。","e":"London is among the largest cities in the world."},{"j":"ロンドンは↑世界↑↓せかい↓↑最大↑↓|さいだい|↓の↑都市↑↓とし↓のひとつである。","e":"London is one of the largest cities in the world."},{"j":"パリは↑世界↑↓せかい↓↑最大↑↓|さいだい|↓の↑都市↑↓とし↓の↑一↑↓ひと↓つである。","e":"Paris is one of the largest cities in the world."},{"j":"ニューヨーク↑州↑↓しゅう↓アーモンクに↑本社↑↓ほんしゃ↓のある↑ＩＢＭ↑↓あいびーえむ↓は↑世界↑↓せかい↓↑最大↑↓|さいだい|↓のコンピューター↑会社↑↓かいしゃ↓です。","e":"International Business Machines Corporation, based in Armonk, New York, is the world's largest computer firm."},{"j":"どんな↑思想↑↓しそう↓が↑中世↑↓ちゅうせい↓のイギリス↑人↑↓じん↓に↑最大↑↓|さいだい|↓の↑影響↑↓えいきょう↓を↑与↑↓あた↓えたと↑思↑↓おも↓いますか。","e":"Which idea do you think had the greatest influence on the English in the Middle Ages?"},{"j":"どこへ↑行↑↓い↓き↑何↑↓なに↓を↑見↑↓み↓るかが↑私↑↓わたし↓の↑最大↑↓|さいだい|↓の↑関心事↑↓かんしんじ↓でした。","e":"Where to go and what to see were my primary concerns."},{"j":"それは↑私↑↓わたし↓が↑今↑↓いま↓までに↑経験↑↓けいけん↓した↑最大↑↓|さいだい|↓の↑喜↑↓よろこ↓びであった。","e":"It was the greatest joy that I have ever experienced."},{"j":"それは↑記録↑↓きろく↓に↑残↑↓のこ↓っている↑最大↑↓|さいだい|↓の↑地震↑↓じしん↓だった。","e":"It was the greatest earthquake on record."},{"j":"その↑年↑↓とし↓の↑日本↑↓にっぽん↓のＯＤＡの↑最大↑↓|さいだい|↓の↑受↑↓う↓け↑手↑↓て↓は↑中国↑↓ちゅうごく↓だった。","e":"The largest recipient of Japan's ODA that year was China."},{"j":"その↑洪水↑↓こうずい↓は↑彼↑↓かれ↓らが↑体験↑↓たいけん↓したうちで↑最大↑↓|さいだい|↓の↑災害↑↓さいがい↓だった。","e":"The flood was the greatest disaster they had ever had."},{"j":"それはこの↑件↑↓けん↓に↑関↑↓かん↓する↑最大↑↓|さいだい|↓の↑問題↑↓もんだい↓↑点↑↓てん↓です。","e":"This is the biggest issue in this matter."},{"j":"そのバスは↑最大↑↓|さいだい|↓↑限度↑↓げんど↓４０↑人↑↓にん↓を↑乗↑↓の↓せることができる。","e":"The bus can carry a maximum of forty people."},{"j":"シドニーはオーストラリアで↑最大↑↓|さいだい|↓の↑都市↑↓とし↓です。","e":"Sydney is the largest city in Australia."},{"j":"シェイクスピアは↑最大↑↓|さいだい|↓の↑劇作↑↓げきさく↓↑家↑↓か↓と↑認↑↓みと↓められている。","e":"Shakespeare is recognized to be the greatest dramatist."},{"j":"シェイクスピアは、イギリスが↑生↑↓う↓んだ↑最大↑↓|さいだい|↓の↑詩人↑↓しじん↓です。","e":"Shakespeare is the greatest poet that England has produced."},{"j":"これはわが↑国↑↓くに↓で↑建造↑↓けんぞう↓された↑最大↑↓|さいだい|↓のタンカーです。","e":"This is the largest tanker that has ever been constructed in our country."},{"j":"これが↑現存↑↓げんそん↓する↑最大↑↓|さいだい|↓の↑建物↑↓たてもの↓です。","e":"This is the largest building in existence."},{"j":"このホールは↑最大↑↓|さいだい|↓で１０００↑人↑↓にん↓↑収容↑↓しゅうよう↓できる。","e":"This hall holds a maximum of 1,000 people."},{"j":"あらゆる↑機会↑↓きかい↓を↑最大限↑↓|さいだい|げん↓に↑利用↑↓りよう↓するようにせよ。","e":"Try to make the most of every opportunity."},{"j":"アメリカ↑経済↑↓けいざい↓は↑世界↑↓せかい↓↑最大↑↓|さいだい|↓です。","e":"The U.S. economy is the largest in the world."},{"j":"チャンスを↑最大限↑↓|さいだい|げん↓に↑活用↑↓かつよう↓してみるべきだよ。","e":"You should try to make the most of your opportunities."},{"j":"↑１９５１↑↓せんきゅうひゃくごじゅういち↓↑年↑↓ねん↓にシスター・テレサは↑当時↑↓とうじ↓インド↑最大↑↓|さいだい|↓の↑都市↑↓とし↓であったカルカッタに↑派遣↑↓はけん↓された。","e":"In 1951, Sister Teresa was sent to Calcutta, then the largest city in India."},{"j":"↑鯨↑↓くじら↓は↑最大↑↓|さいだい|↓の↑哺乳↑↓ほにゅう↓↑動物↑↓どうぶつ↓であることはよく↑知↑↓し↓られている。","e":"The whale is well known to be the largest mammal."}]}