{"data":{"k_ele":[{"e":"女子","p":true}],"r_ele":[{"r":"じょし","p":true},{"r":"おなご"},{"r":"おみなご","i":["ok"]}],"sense":[{"gloss":"woman, girl","pos":["n"]}]},"sdata":[{"j":"↑君↑↓きみ↓の↑論文↑↓ろんぶん↓から↑不必要↑↓ふひつよう↓な↑語↑↓かたり↓を↑削除↑↓さく|じょ↓し|た↑方↑↓ほう↓がよろしい。","e":"Omit needless words!"},{"j":"↑君↑↓きみ↓が↑最善↑↓さいぜん↓を↑尽↑↓つ↓くすかぎりは↑君↑↓きみ↓を↑援助↑↓えん|じょ↓し|てあげよう。","e":"I'll help you so long as you do your best."},{"j":"↑議長↑↓ぎちょう↓は↑意見↑↓いけん↓が↑不一致↑↓ふいっち↓に↑終↑↓おわ↓る↑可能↑↓かのう↓↑性↑↓せい↓を↑排除↑↓はい|じょ↓し|なかった。","e":"The chairman did not rule out the possibility of a disagreement."},{"j":"↑喜↑↓よろこ↓んで↑君↑↓きみ↓を↑援助↑↓えん|じょ↓し|てあげよう。","e":"I will gladly help you."},{"j":"↑学生↑↓がくせい↓たちは↑教授↑↓きょうじゅ↓の↑調査↑↓ちょうさ↓の↑助手↑↓|じょし|ゅ↓を↑務↑↓つと↓めた。","e":"The students assisted the professor in the investigation."},{"j":"↑一般↑↓いっぱん↓に↑男子↑↓だんし↓は↑女子↑↓|じょし|↓より↑速↑↓はや↓く↑走↑↓はし↓ることができる。","e":"Generally speaking, boys can run faster than girls."},{"j":"↑一般↑↓いっぱん↓に↑男子↑↓だんし↓は↑女子↑↓|じょし|↓よりも↑足↑↓あし↓が↑速↑↓はや↓い。","e":"Generally speaking, boys can run faster than girls."},{"j":"↑一般↑↓いっぱん↓に↑女子↑↓|じょし|↓よりも↑男子↑↓だんし↓の↑方↑↓ほう↓が↑足↑↓あし↓が↑速↑↓はや↓い。","e":"Generally speaking, boys can run faster than girls."},{"j":"↑我々↑↓われわれ↓は↑彼↑↓かれ↓が↑援助↑↓えん|じょ↓し|てくれると↑思↑↓おも↓います。","e":"We expect that he'll help us."},{"j":"↑我々↑↓われわれ↓は↑援助↑↓えん|じょ↓し|なかったので↑彼↑↓かれ↓は↑自力↑↓じりき↓でやり↑遂↑↓と↓げた。","e":"We didn't help him, so he did it off his own bat."}]}