{"data":{"k_ele":[{"e":"徐行","p":true}],"r_ele":[{"r":"じょこう","p":true}],"sense":[{"gloss":"going slowly (of a car, train, etc.)","pos":["n","vs","vi"]}]},"sdata":[{"j":"タイタニック↑号↑↓ごう↓は↑処女↑↓しょ|じょ↓↑航海↑↓こう|かい↓で↑沈没↑↓ちんぼつ↓した。","e":"The Titanic sunk on its maiden voyage."},{"j":"1912↑年↑↓ねん↓、タイタニック↑号↑↓ごう↓は↑処女↑↓しょ|じょ↓↑航海↑↓こう|かい↓↑中↑↓ちゅう↓に↑沈没↑↓ちんぼつ↓した。","e":"It was in 1912 that the Titanic sank during her first voyage."},{"j":"↑車↑↓くるま↓に↑徐行↑↓|じょこう|↓するようにと↑合図↑↓あいず↓した。","e":"I signaled the car to go slow."},{"j":"↑彼女↑↓かの|じょ↓↑好調↑↓こう|ちょう↓ですね。","e":"She's on a roll."},{"j":"↑援助↑↓えん|じょ↓↑交際↑↓こう|さい↓をほのめかすネット↑掲示板↑↓けいじばん↓に↑書↑↓か↓き↑込↑↓こ↓んだ↑女子高↑↓じょしこう↓↑生↑↓せい↓が↑検挙↑↓けんきょ↓されました。","e":"A high school girl posting on a web forum hinting at underaged prostitution has been arrested."},{"j":"↑車↑↓くるま↓が↑徐行↑↓|じょこう|↓でついてきているような↑気↑↓き↓がする。","e":"I think that that car is slowly following us."},{"j":"タイタニックの↑処女↑↓しょ|じょ↓↑航海↑↓こう|かい↓はあまり↑良↑↓よ↓くなかったです。","e":"The Titanic's maiden voyage didn't go so well."}]}