{"data":{"k_ele":[{"e":"自衛","p":true}],"r_ele":[{"r":"じえい","p":true}],"sense":[{"gloss":"self-defense, self-defence","pos":["n","vs","vt","vi","adj-no"]}]},"sdata":[{"j":"ジョンソン↑氏↑↓し↓は↑自営業↑↓|じえい|ぎょう↓で、↑家具↑↓かぐ↓の↑修理↑↓しゅうり↓をやっている。","e":"Mr Johnson is self-employed and is in the business of repairing furniture."},{"j":"↑自営業↑↓|じえい|ぎょう↓の↑方↑↓ほう↓がいい。","e":"I prefer to work on my own."},{"j":"↑当時↑↓とう|じ↓↑英国↑↓えい|こく↓は↑戦争↑↓せんそう↓の↑準備↑↓じゅんび↓ができていなかった。","e":"Britain was not geared up for war then."},{"j":"↑彼↑↓かれ↓は↑自営業↑↓|じえい|ぎょう↓をしていた。","e":"He did the work on his own."},{"j":"ボーイング↑社↑↓しゃ↓は↑海上↑↓かいじょう↓↑自衛隊↑↓|じえい|たい↓↑用↑↓よう↓の↑飛行↑↓ひこう↓↑艇↑↓てい↓を↑開発↑↓かいはつ↓しました。","e":"Boeing developed a flying boat for the Maritime Self-Defense Force."},{"j":"↑政府↑↓せいふ↓が↑自衛隊↑↓|じえい|たい↓に↑沖縄↑↓おきなわ↓への↑災害↑↓さいがい↓↑派遣↑↓はけん↓を↑要請↑↓ようせい↓した。","e":"The government asked the SDF for a disaster relief deployment to Okinawa."},{"j":"↑過去↑↓かこ↓に↑陸上↑↓りくじょう↓↑自衛隊↑↓|じえい|たい↓↑演習↑↓えんしゅう↓↑場↑↓じょう↓で↑行↑↓おこな↓われた↑射撃↑↓しゃげき↓↑訓練↑↓くんれん↓で、↑砲弾↑↓ほうだん↓が↑場外↑↓じょうがい↓に↑着弾↑↓ちゃくだん↓する↑事故↑↓じこ↓が↑起↑↓お↓きている。","e":"In the past accidents have occurred where shells fell outside of the firing range area used for exercises by the JGSDF."},{"j":"トムは↑自営↑↓|じえい|↓の↑配管↑↓はいかん↓↑工↑↓こう↓だ。","e":"Tom is a self-employed plumber."}]}