{"data":{"k_ele":[{"e":"卒業後","p":true}],"r_ele":[{"r":"そつぎょうご","p":true}],"sense":[{"gloss":"after graduation","pos":["n","adv"]}]},"sdata":[{"j":"↑高校↑↓こうこう↓↑卒業↑↓|そつぎょう↓↑後↑↓ご|↓、↑彼↑↓かれ↓は↑大学↑↓だいがく↓へ↑進↑↓すす↓み、↑父↑↓ちち↓↑同様↑↓どうよう↓↑牧師↑↓ぼくし↓になるための↑勉強↑↓べんきょう↓をした。","e":"After high school, he went to college and studied to be a minister, like his father."},{"j":"↑姉↑↓あね↓は↑学校↑↓がっこう↓を↑卒業↑↓|そつぎょう↓↑後↑↓ご|↓は↑海外↑↓かいがい↓↑留学↑↓りゅうがく↓したいそうです。","e":"My sister says that she wants to study abroad after leaving."},{"j":"↑彼↑↓かれ↓は↑卒業↑↓|そつぎょう↓↑後↑↓ご|↓、↑研究↑↓けんきゅう↓に↑従事↑↓じゅうじ↓するだろう。","e":"After graduation he will engage himself in study."},{"j":"↑彼↑↓かれ↓は↑大学↑↓だいがく↓↑卒業↑↓|そつぎょう↓↑後↑↓ご|↓↑日本↑↓にっぽん↓に↑戻↑↓もど↓った。","e":"He returned to Japan after graduating from college."},{"j":"↑彼↑↓かれ↓は↑大学↑↓だいがく↓↑卒業↑↓|そつぎょう↓↑後↑↓ご|↓１０↑年間↑↓ねんかん↓↑親↑↓おや↓のすねをかじって↑生活↑↓せいかつ↓してきた。","e":"He has lived off his parents for ten years since he graduated from college."},{"j":"↑彼↑↓かれ↓は↑大学↑↓だいがく↓↑卒業↑↓|そつぎょう↓↑後↑↓ご|↓カメラマンになった。","e":"He became a cameraman after he graduated from college."},{"j":"↑彼女↑↓かのじょ↓は↑大学↑↓だいがく↓↑卒業↑↓|そつぎょう↓↑後↑↓ご|↓まもなく↑結婚↑↓けっこん↓した。","e":"She got married soon after her graduation from the college."},{"j":"↑卒業↑↓|そつぎょう↓↑後↑↓ご|↓はどうするつもりなの？","e":"What do you plan to do after graduation?"},{"j":"↑卒業↑↓|そつぎょう↓↑後↑↓ご|↓はどうするつもりなの？","e":"What will you do after graduation?"},{"j":"↑卒業↑↓|そつぎょう↓↑後↑↓ご|↓はどうするつもりなの？","e":"What'll you do after graduation?"}]}