{"data":{"k_ele":[{"e":"天地","p":true}],"r_ele":[{"r":"てんち","p":true},{"r":"あめつち"}],"sense":[{"gloss":"heaven and earth, the universe, the world, nature","pos":["n"]},{"gloss":"land, world, realm, sphere","pos":["n"]},{"gloss":"top and bottom","pos":["n"]},{"gloss":"gods of heaven and earth","pos":["n"]}]},"sdata":[{"j":"↑運転↑↓うん|てん↓↑中↑↓ち|ゅう↓は↑彼↑↓かれ↓に↑話↑↓はな↓し↑掛↑↓か↓けてはいけません。","e":"Don't speak to him while he is driving."},{"j":"↑運転↑↓うん|てん↓↑中↑↓ち|ゅう↓は↑救急↑↓きゅうきゅう↓↑車↑↓しゃ↓には↑道↑↓みち↓を↑譲↑↓ゆず↓らなければいけない。","e":"When you are driving, you should make way for ambulances."},{"j":"↑運転↑↓うん|てん↓↑中↑↓ち|ゅう↓は↑運転↑↓うんてん↓↑手↑↓しゅ↓に↑話↑↓はな↓しかけぬこと。","e":"Passengers shall not converse with the driver while the bus is in motion."},{"j":"↑運転↑↓うん|てん↓↑中↑↓ち|ゅう↓はシートベルトを↑締↑↓し↓めなさい。","e":"Fasten your seat belts while you are driving."},{"j":"↑運転↑↓うん|てん↓↑中↑↓ち|ゅう↓にドライバーに↑話↑↓はな↓し↑掛↑↓か↓けてはいけません。","e":"Don't speak to the driver while he is driving."},{"j":"↑医者↑↓いしゃ↓は↑転地↑↓|てんち|↓を↑勧↑↓すす↓めた。","e":"The doctor advised a change of air."},{"j":"↑医者↑↓いしゃ↓が↑勧↑↓すす↓めるので、どこかへ↑転地↑↓|てんち|↓↑療養↑↓りょうよう↓に↑行↑↓い↓こうと↑思↑↓おも↓っています。","e":"I'm thinking of going somewhere for a change of air, since my doctor advises me to."},{"j":"その↑機械↑↓きかい↓は↑今↑↓いま↓↑運転↑↓うん|てん↓↑中↑↓ち|ゅう↓だ。","e":"The machine is now in operation."},{"j":"シドニー↑支店↑↓し|てん↓↑長↑↓ち|ょう↓に↑就任↑↓しゅうにん↓すると↑伺↑↓うかが↓いました。","e":"I heard you have become Branch Manager of the Sydney office."},{"j":"この↑店↑↓みせ↓の↑店長↑↓|てんち|ょう↓はひげが↑生↑↓は↓えています。","e":"The manager of this store is growing a beard."}]}