{"data":{"k_ele":[{"e":"手伝い","p":true},{"e":"手つだい"}],"r_ele":[{"r":"てつだい","p":true}],"sense":[{"gloss":"helper, assistant","pos":["n"]},{"gloss":"help, assistance","pos":["n"]}]},"sdata":[{"j":"↑君↑↓きみ↓が↑忙↑↓いそが↓しいなら↑僕↑↓ぼく↓が↑手伝↑↓|てつだ↓い|ましょう。","e":"If you're busy, I'll help you."},{"j":"↑恐縮↑↓きょうしゅく↓ですがお↑手伝↑↓|てつだ↓い|↑願↑↓ねが↓えませんか。","e":"May I make so bold as to request your assistance?"},{"j":"↑及↑↓およ↓ばずながらお↑手伝↑↓|てつだ↓い|しましょう。","e":"I will help you all I can."},{"j":"↑大↑↓おお↓いに↑喜↑↓よろこ↓んでお↑手伝↑↓|てつだ↓い|いたしましょう。","e":"I'll be only too pleased to help you."},{"j":"↑喜↑↓よろこ↓んでお↑手伝↑↓|てつだ↓い|いたしましょう。","e":"I'll be only too pleased to help you."},{"j":"↑喜↑↓よろこ↓んで↑彼↑↓かれ↓を↑手伝↑↓|てつだ↓い|ましょう。","e":"I'll be glad to help him."},{"j":"↑喜↑↓よろこ↓んでお↑手伝↑↓|てつだ↓い|しますよ。","e":"I will be glad to help you."},{"j":"よろこんでお↑手伝↑↓|てつだ↓い|しましょう。","e":"I will be glad to help you."},{"j":"↑喜↑↓よろこ↓んであなたのお↑手伝↑↓|てつだ↓い|をします。","e":"I will be pleased to help you."},{"j":"↑学生↑↓がくせい↓たちは↑自発↑↓じはつ↓↑的↑↓てき↓に↑村人↑↓むらびと↓の↑手伝↑↓|てつだ↓い|にやってきた。","e":"Students came of their own accord to help the villagers."}]}