{"data":{"k_ele":[{"e":"挽歌","p":true}],"r_ele":[{"r":"ばんか","p":true}],"sense":[{"gloss":"elegy, funeral song","pos":["n","adj-no"]}]},"sdata":[{"j":"あなたは↑今晩↑↓こん|ばん↓↑彼↑↓か|れ↓の↑家↑↓いえ↓で↑彼↑↓かれ↓と↑連絡↑↓れんらく↓が↑取↑↓と↓れる。","e":"You can get in touch with him at his home tonight."},{"j":"↑一番↑↓いち|ばん↓↑下↑↓か|↓の↑妹↑↓いもうと↓が↑出世↑↓しゅっせ↓したとき↑私↑↓わたし↓は↑我↑↓われ↓を↑忘↑↓わす↓れて↑嫉妬↑↓しっと↓した。","e":"I was beside myself with jealousy when my youngest sister rose in the world."},{"j":"↑一番↑↓いち|ばん↓↑下↑↓か|↓の↑弟↑↓おとうと↓は、↑祖母↑↓そぼ↓に↑育↑↓そだ↓てられた。","e":"My youngest brother was brought up by our grandmother."},{"j":"↑一番↑↓いち|ばん↓↑下↑↓か|↓の↑子↑↓こ↓は↑毎日↑↓まいにち↓↑午前↑↓ごぜん↓↑中↑↓ちゅう↓を↑保育園↑↓ほいくえん↓ですごしました。","e":"The youngest child spent every morning at a nursery."},{"j":"↑一↑↓いち↓↑晩↑↓|ばん↓↑彼↑↓か|れ↓を↑泊↑↓と↓めることができる。","e":"We can accommodate him for the night."},{"j":"ほかの↑条件↑↓じょうけん↓が↑同↑↓おな↓じなら、↑一番↑↓いち|ばん↓↑簡単↑↓か|んたん↓な↑説明↑↓せつめい↓が↑一番↑↓いちばん↓よい。","e":"Other things being equal, the simplest explanation is the best."},{"j":"メアリーはクラスの↑女子↑↓じょし↓の↑中↑↓なか↓で↑一番↑↓いち|ばん↓↑歌↑↓か|↓が↑上手↑↓うま↓い。","e":"Mary sings best of all of the girls in class."},{"j":"メアリーはクラスで↑一番↑↓いち|ばん↓か|わいい↑女↑↓おんな↓の↑子↑↓こ↓です。","e":"Mary is the prettiest girl in her class."},{"j":"その↑男↑↓おとこ↓は、↑終身↑↓しゅうしん↓↑刑↑↓けい↓であると↑裁判官↑↓さい|ばんか|ん↓が↑判決↑↓はんけつ↓を↑下↑↓くだ↓した↑時↑↓とき↓、↑取↑↓と↓り↑乱↑↓みだ↓した。","e":"The man went to pieces when the judge said he would have to go to prison for life."},{"j":"その↑事件↑↓じけん↓の↑裁判官↑↓さい|ばんか|ん↓は↑誰↑↓だれ↓ですか。","e":"Who will try the case?"},{"j":"その↑裁判官↑↓さい|ばんか|ん↓は↑厳粛↑↓げんしゅく↓な↑顔↑↓かお↓をして、↑怖↑↓こわ↓そうに↑見↑↓み↓えた。","e":"The judge was grave and forbidding."},{"j":"その↑裁判官↑↓さい|ばんか|ん↓は、↑最終↑↓さいしゅう↓↑判決↑↓はんけつ↓をひるがえした。","e":"The judge reversed the final decision."},{"j":"その↑金↑↓きん↓は↑彼↑↓かれ↓のか|ばんか|ら↑盗↑↓ぬす↓まれた。","e":"The money was stolen from his briefcase."},{"j":"こんな↑裁判官↑↓さい|ばんか|ん↓は、↑定年↑↓ていねん↓より↑前↑↓まえ↓に↑引退↑↓いんたい↓する↑方↑↓ほう↓がよい。","e":"Such a judge should retire from his job before retirement age."},{"j":"これは↑今↑↓いま↓まで↑見↑↓み↓た↑中↑↓なか↓で↑一番↑↓いち|ばん↓か|わいい↑赤↑↓あか↓ちゃんです。","e":"This is the cutest baby that I have ever seen."},{"j":"ケイトはクラスで↑一番↑↓いち|ばん↓↑歌↑↓か|↓がうまい。","e":"Kate is the best singer in my class."},{"j":"ケイトはクラスの↑中↑↓なか↓で↑一番↑↓いち|ばん↓↑歌↑↓か|↓が↑上手↑↓じょうず↓です。","e":"Kate is the best singer in my class."},{"j":"うちの↑会社↑↓かいしゃ↓で↑誰↑↓だれ↓が↑一番↑↓いち|ばん↓↑歌↑↓か|↓がうまい？","e":"Who is the best singer in our company?"},{"j":"ある↑晩↑↓|ばん↓↑彼↑↓か|れ↓は、すっかり↑疲↑↓つか↓れ↑憂鬱↑↓ゆううつ↓になって↑帰↑↓かえ↓ってきた。","e":"One night he came home very tired and sad."},{"j":"アメリカの↑法↑↓ほう↓システムでは、↑裁判官↑↓さい|ばんか|ん↓は１２↑人↑↓にん↓です。","e":"In the justice system of the United States, there are twelve people on a jury."},{"j":"あなたは↑今晩↑↓こん|ばん↓↑家↑↓か|↓にいますか。","e":"Will you stay at home tonight?"},{"j":"あなたの↑組↑↓くみ↓でどの↑子↑↓こ↓が↑一番↑↓いち|ばん↓↑歌↑↓か|↓がうまいですか。","e":"Who sings the best of all the boys in your class?"},{"j":"あなたの↑一番↑↓いち|ばん↓↑下↑↓か|↓の↑弟↑↓おとうと↓は↑背丈↑↓せたけ↓がどのくらいですか。","e":"How tall is your youngest brother?"},{"j":"１↑泊↑↓はく↓５０ドルくらいのダブルの↑部屋↑↓へや↓を↑一↑↓いち↓↑室↑↓しつ↓、↑今晩↑↓こん|ばん↓か|ら４↑泊↑↓はく↓お↑願↑↓ねが↓いします。","e":"I'd like a double for four nights from tonight for about fifty dollars a night."},{"j":"↑決↑↓き↓めた！↑今晩↑↓こん|ばん↓↑彼↑↓か|れ↓をデートに↑誘↑↓さそ↓うわ。","e":"I decided. I'm going to ask him out tonight."},{"j":"↑今晩↑↓こん|ばん↓か|ら↑三↑↓さん↓↑泊↑↓はく↓、↑予約↑↓よやく↓をしてあります。","e":"I have a reservation for three nights from tonight."},{"j":"↑今晩↑↓こん|ばん↓↑彼↑↓か|れ↓に↑電話↑↓でんわ↓するよ。","e":"I'll call him tonight."},{"j":"↑今晩↑↓こん|ばん↓↑彼↑↓か|れ↓の↑家出↑↓いえで↓↑集↑↓あつ↓まりがある。","e":"We will have a meeting at his house this evening."},{"j":"↑今晩↑↓こん|ばん↓↑彼↑↓か|れ↓の↑送別↑↓そうべつ↓↑会↑↓かい↓をするんだよ。","e":"We are giving a farewell party for him tonight."},{"j":"↑裁判官↑↓さい|ばんか|ん↓が↑有罪↑↓ゆうざい↓の↑判決↑↓はんけつ↓を↑下↑↓くだ↓した↑以上↑↓いじょう↓、いさぎよく↑服役↑↓ふくえき↓しなければならない。","e":"The judge pronounced him \"guilty\", and now he must face the music of a sentence in prison."},{"j":"↑裁判官↑↓さい|ばんか|ん↓には↑慎重↑↓しんちょう↓さがなくてはならない。","e":"Discretion is proper to judges."},{"j":"ヤッパリさんが↑裁判官↑↓さい|ばんか|ん↓に↑慈悲↑↓じひ↓を↑求↑↓もと↓めて↑訴↑↓うった↓えた。","e":"Mr. Yappari appealed to the judge for mercy."},{"j":"↑裁判官↑↓さい|ばんか|ん↓は、その↑囚人↑↓しゅうじん↓が↑無罪↑↓むざい↓だと↑結論↑↓けつろん↓をくだした。","e":"The judge concluded that the prisoner was innocent."},{"j":"↑裁判官↑↓さい|ばんか|ん↓は、それが↑初犯↑↓しょはん↓であることを↑考慮↑↓こうりょ↓に↑入↑↓い↓れた。","e":"The judge took into consideration the fact that it was his first offense."},{"j":"↑裁判官↑↓さい|ばんか|ん↓はその↑囚人↑↓しゅうじん↓が↑有罪↑↓ゆうざい↓であると↑決断↑↓けつだん↓を↑下↑↓くだ↓した。","e":"The judge concluded that the prisoner was guilty."},{"j":"↑裁判官↑↓さい|ばんか|ん↓はその↑囚人↑↓しゅうじん↓の↑一↑↓いち↓↑年↑↓ねん↓の↑刑期↑↓けいき↓を↑赦免↑↓しゃめん↓した。","e":"The judge pardoned the prisoner a year of his sentence."},{"j":"↑裁判官↑↓さい|ばんか|ん↓はその↑未決囚↑↓みけつしゅう↓の↑行動↑↓こうどう↓に↑対↑↓たい↓する↑嫌悪↑↓けんお↓の↑念↑↓ねん↓をためらうことなくあからさまにして、できるだけ↑過酷↑↓かこく↓な↑刑↑↓けい↓を↑下↑↓くだ↓した。","e":"The judge made no bones about his disgust with the accused's actions and handed down the severest sentence possible."},{"j":"↑裁判官↑↓さい|ばんか|ん↓は↑思↑↓おも↓わず↑笑↑↓わら↓った。","e":"The judge laughed in spite of himself."},{"j":"↑裁判官↑↓さい|ばんか|ん↓はついうっかり↑笑↑↓わら↓ってしまった。","e":"The judge laughed in spite of himself."},{"j":"↑裁判官↑↓さい|ばんか|ん↓は↑原告↑↓げんこく↓に↑不利↑↓ふり↓な↑判決↑↓はんけつ↓を↑下↑↓くだ↓した。","e":"The judge decided against the plaintiff."}]}