{"data":{"k_ele":[{"e":"左側","p":true}],"r_ele":[{"r":"ひだりがわ","p":true},{"r":"さそく"},{"r":"ひだりっかわ","i":["sk"]}],"sense":[{"gloss":"left side, left-hand side","pos":["n","adj-no"]}]},"sdata":[{"j":"↑左側↑↓|ひだりがわ|↓に↑秘密↑↓ひみつ↓の↑通路↑↓つうろ↓がある。","e":"There's a secret path on the left."},{"j":"もう３ブロック↑行↑↓い↓けば↑左側↑↓|ひだりがわ|↓に↑博物館↑↓はくぶつかん↓があります。","e":"Walk three more blocks and you will find the museum on your left."},{"j":"ボールは↑彼↑↓かれ↓の↑頭↑↓あたま↓の↑左側↑↓|ひだりがわ|↓に↑当↑↓あ↓たった。","e":"The ball hit him on the left side of the head."},{"j":"それは↑通↑↓とお↓りの↑左側↑↓|ひだりがわ|↓にある。","e":"It is on the left side of the street."},{"j":"ジムはまだ↑路上↑↓ろじょう↓での↑左側↑↓|ひだりがわ|↓↑運転↑↓うんてん↓に↑慣↑↓な↓れていない。","e":"Jim is not yet used to driving on the left side of the road."},{"j":"この↑道↑↓みち↓をまっすぐ↑行↑↓おこな↓ったところの↑左側↑↓|ひだりがわ|↓がありますよ。","e":"It's just down the street on your left."},{"j":"この↑通↑↓とお↓りをいくと↑郵便↑↓ゆうびん↓↑局↑↓きょく↓は↑左側↑↓|ひだりがわ|↓にあります。","e":"Go along this street and you'll come to the post office on the left."},{"j":"イギリスでは↑人々↑↓ひとびと↓は↑左側↑↓|ひだりがわ|↓↑通行↑↓つうこう↓をすることになっています。","e":"In England they are supposed to keep to the left."},{"j":"イギリスでは↑車↑↓くるま↓は↑左側↑↓|ひだりがわ|↓↑通行↑↓つうこう↓だ。","e":"They drive on the left in England."},{"j":"あなたの↑左側↑↓|ひだりがわ|↓にその↑店↑↓みせ↓が↑見↑↓み↓えます。","e":"You'll see the store on your left."}]}