{"data":{"k_ele":[{"e":"目茶目茶","p":true,"i":["ateji"]},{"e":"滅茶滅茶","i":["ateji"]}],"r_ele":[{"r":"めちゃめちゃ","p":true},{"r":"メチャメチャ"}],"sense":[{"gloss":"disorderly, messy, ruined","pos":["adj-na","n"]},{"gloss":"absurd, unreasonable, excessive, rash","pos":["adj-na","n"]},{"gloss":"very, extremely","pos":["adv"]}],"m":["uk","yoji"]},"sdata":[{"j":"↑一体↑↓いったい↓だれが↑私↑↓わたし↓の↑名簿↑↓めいぼ↓を|めちゃめちゃ|にしたのだ。","e":"Who's gone and messed up my list of names?"},{"j":"とても↑高価↑↓こうか↓な↑陶器↑↓とうき↓が|めちゃめちゃ|に↑割↑↓わ↓れてしまった。","e":"The priceless china shattered into fragments."},{"j":"↑自転車↑↓じてんしゃ↓はトラックに↑衝突↑↓しょうとつ↓して|めちゃめちゃ|になった。","e":"The bike was mangled in its collision with the truck."},{"j":"トムって|めちゃめちゃ|↑忘↑↓わす↓れっぽいよね？","e":"Tom is very forgetful, isn't he?"},{"j":"↑私↑↓わたし↓、それ|めちゃめちゃ|↑大好↑↓だいす↓きなのよ。","e":"I really do love it."},{"j":"このスーツケース、|めちゃめちゃ|↑重↑↓おも↓たいな。","e":"This suitcase is very heavy."},{"j":"|めちゃめちゃ|↑楽↑↓たの↓しかったよ。","e":"It was great fun."},{"j":"あの↑男↑↓おとこ↓の↑子↑↓こ↓、|めちゃめちゃ|↑頭↑↓あたま↓いいんだよ。","e":"That boy is very smart."},{"j":"|めちゃめちゃ|↑忙↑↓いそが↓しくて、↑本↑↓ほん↓を↑読↑↓よ↓む↑時間↑↓じかん↓なんてないよ。","e":"I'm so busy that I have no time to read."},{"j":"↑俺↑↓おれ↓は|めちゃめちゃ|↑冷静↑↓れいせい↓だったぞ。","e":"I was as cool as a cucumber."},{"j":"↑今日↑↓きょう↓は|めちゃめちゃ|↑暑↑↓あつ↓いよ。","e":"It is very hot today."},{"j":"このスーツケース、|めちゃめちゃ|↑重↑↓おも↓たいな。","e":"This suitcase is really heavy."},{"j":"|めちゃめちゃ|お↑腹↑↓なか↓が↑痛↑↓いた↓かったんだ。","e":"I had a bad stomachache."},{"j":"↑今日↑↓きょう↓って、|めちゃめちゃ|↑寒↑↓さむ↓くない？","e":"It is very cold today, isn't it?"},{"j":"|めちゃめちゃ|↑寒↑↓さむ↓くなったね。","e":"It has become very cold."},{"j":"ピアノって、|めちゃめちゃ|↑高↑↓たか↓いよな？","e":"Pianos are really expensive, aren't they?"},{"j":"|めちゃめちゃ|↑忙↑↓いそが↓しくて、↑本↑↓ほん↓を↑読↑↓よ↓む↑時間↑↓じかん↓なんてないよ。","e":"I am so busy that I have no time to read."},{"j":"|めちゃめちゃ|↑忙↑↓いそが↓しくて、↑本↑↓ほん↓を↑読↑↓よ↓む↑時間↑↓じかん↓なんてないよ。","e":"I'm so busy I have no time to read."},{"j":"↑土曜日↑↓どようび↓の↑海水浴↑↓かいすいよく↓↑場↑↓じょう↓って、|めちゃめちゃ|↑混↑↓こ↓んでるよ。","e":"The beaches are very crowded on Saturdays."},{"j":"トムはピアノが|めちゃめちゃ|↑上手↑↓うま↓いんだ。","e":"Tom can play piano very well."},{"j":"「トムってすごいんだよ。|めちゃめちゃ|↑高↑↓こう↓↑得点↑↓とくてん↓↑出↑↓だ↓してたんだ」「まぐれだよ。あいつがそんなに↑上手↑↓うま↓いはずないもん」","e":"Tom's killing it! That's one crazy high score. \"It's a fluke. He can't be that good.\""},{"j":"メアリーがボストンを↑離↑↓はな↓れたってトムから↑聞↑↓き↓いたときは、|めちゃめちゃ|↑驚↑↓おどろ↓いたよ。","e":"I was very surprised when Tom told me Mary had left Boston."},{"j":"↑朝↑↓あさ↓ご↑飯↑↓はん↓に↑何↑↓なん↓にも↑食↑↓た↓べなかったから、↑今↑↓いま↓|めちゃめちゃ|↑腹↑↓はら↓↑減↑↓へ↓ってるよ。","e":"Since I didn't eat anything for breakfast, I'm very hungry now."}]}