{"data":{"k_ele":[{"e":"持ち物","p":true},{"e":"持物"},{"e":"持ちもの","i":["sK"]}],"r_ele":[{"r":"もちもの","p":true}],"sense":[{"gloss":"one's property, personal effects, one's belongings","pos":["n"]}]},"sdata":[{"j":"↑君↑↓きみ↓の↑持↑↓|も↓ち↑物↑↓もの|↓はどこにあるのですか。","e":"Where are your things?"},{"j":"どの↑電車↑↓でんしゃ↓も↑満員↑↓まんいん↓で、↑持↑↓|も↓ち↑物↑↓もの|↓も↑手↑↓て↓から↑放↑↓はな↓しても↑落↑↓お↓ちないほどです。","e":"But every train is so crowded that whatever we have in our hands doesn't fall even if we let it go."},{"j":"この↑本↑↓ほん↓はあなたの↑持↑↓|も↓ち↑物↑↓もの|↓ですか？","e":"Does this book belong to you?"},{"j":"↑私↑↓わたし↓の↑持↑↓|も↓ち↑物↑↓もの|↓には↑触↑↓さわ↓らないで。","e":"Let my things alone."},{"j":"↑私↑↓わたし↓の↑持↑↓|も↓ち↑物↑↓もの|↓に↑触↑↓ふ↓れないでください。","e":"Please leave my things alone."},{"j":"↑私↑↓わたし↓は↑持↑↓|も↓ち↑物↑↓もの|↓↑全部↑↓ぜんぶ↓と↑一緒↑↓いっしょ↓に↑家↑↓いえ↓からほうり↑出↑↓だ↓された。","e":"I was thrown out of the house bag and baggage."},{"j":"↑持↑↓|も↓ち↑物↑↓もの|↓をまとめなさい。","e":"Get your things together."},{"j":"↑自分↑↓じぶん↓の↑持↑↓|も↓ち↑物↑↓もの|↓を↑忘↑↓わす↓れないように。","e":"Don't leave your things behind."},{"j":"↑持↑↓|も↓ち↑物↑↓もの|↓を↑置↑↓お↓き↑忘↑↓わす↓れないように。","e":"Don't leave your things behind."},{"j":"↑自分↑↓じぶん↓の↑持↑↓|も↓ち↑物↑↓もの|↓を↑忘↑↓わす↓れるな。","e":"Don't leave your things behind."},{"j":"↑持↑↓|も↓ち↑物↑↓もの|↓を↑忘↑↓わす↓れないように↑気↑↓き↓をつけなさい。","e":"Be sure to take all your belongings with you."},{"j":"↑自分↑↓じぶん↓の↑持↑↓|も↓ち↑物↑↓もの|↓には↑全↑↓すべ↓て↑名前↑↓なまえ↓をつけなさい。","e":"Put your name on all your belongings."},{"j":"↑自分↑↓じぶん↓の↑持↑↓|も↓ち↑物↑↓もの|↓を↑忘↑↓わす↓れないように。","e":"Don't leave your stuff behind."},{"j":"↑自分↑↓じぶん↓の↑持↑↓|も↓ち↑物↑↓もの|↓を↑忘↑↓わす↓れるな。","e":"Don't leave your stuff behind."},{"j":"↑人↑↓ひと↓の↑価値↑↓かち↓は↑持↑↓|も↓ち↑物↑↓もの|↓というより↑人↑↓ひと↓となりにある。","e":"A man's worth lies not so much in what he has as in what he is."},{"j":"↑彼↑↓かれ↓らはジムから↑持↑↓|も↓ち↑物↑↓もの|↓をすべて↑奪↑↓うば↓った。","e":"They robbed Jim of everything he had."},{"j":"↑彼女↑↓かのじょ↓は↑持↑↓|も↓ち↑物↑↓もの|↓↑全部↑↓ぜんぶ↓を↑持↑↓も↓って↑家出↑↓いえで↓した。","e":"She left home bag and baggage."},{"j":"↑妹↑↓いもうと↓は↑自分↑↓じぶん↓のすべての↑持↑↓|も↓ち↑物↑↓もの|↓を↑大切↑↓たいせつ↓にする。","e":"My sister takes care of everything she possesses."},{"j":"↑静↑↓しず↓かに！みんなその↑場↑↓ば↓を↑動↑↓うご↓かないで。これから↑持↑↓|も↓ち↑物↑↓もの|↓↑検査↑↓けんさ↓をはじめます。","e":"Quiet! Everybody stay where they are, there will now be a possessions check."},{"j":"↑持↑↓|も↓ち↑物↑↓もの|↓すべてに↑記名↑↓きめい↓してください。","e":"Please put their name on everything they take with them."},{"j":"↑彼女↑↓かのじょ↓は↑持↑↓|も↓ち↑物↑↓もの|↓↑全部↑↓ぜんぶ↓を↑持↑↓も↓って↑家出↑↓いえで↓した。","e":"She left home with everything she owned."},{"j":"↑私↑↓わたし↓は↑持↑↓|も↓ち↑物↑↓もの|↓↑全部↑↓ぜんぶ↓と↑一緒↑↓いっしょ↓に↑家↑↓いえ↓からほうり↑出↑↓だ↓された。","e":"I was thrown out of the house with everything I owned."},{"j":"↑自分↑↓じぶん↓の↑持↑↓|も↓ち↑物↑↓もの|↓を↑忘↑↓わす↓れないように。","e":"Don't forget your things."},{"j":"↑自分↑↓じぶん↓の↑持↑↓|も↓ち↑物↑↓もの|↓を↑忘↑↓わす↓れるな。","e":"Don't forget your things."},{"j":"↑自分↑↓じぶん↓の↑持↑↓|も↓ち↑物↑↓もの|↓を↑忘↑↓わす↓れないように。","e":"Don't forget your stuff."},{"j":"↑自分↑↓じぶん↓の↑持↑↓|も↓ち↑物↑↓もの|↓を↑忘↑↓わす↓れるな。","e":"Don't forget your stuff."},{"j":"↑私↑↓わたし↓の↑持↑↓|も↓ち↑物↑↓もの|↓には↑触↑↓さわ↓らないで。","e":"Leave my stuff alone."},{"j":"↑私↑↓わたし↓の↑持↑↓|も↓ち↑物↑↓もの|↓には↑触↑↓さわ↓らないで。","e":"Leave my things alone."},{"j":"↑自分↑↓じぶん↓の↑持↑↓|も↓ち↑物↑↓もの|↓には↑全↑↓すべ↓て↑名前↑↓なまえ↓を↑書↑↓か↓いておくこと。","e":"Put your name on all your belongings."}]}