{"data":{"r_ele":[{"r":"グラス","p":true}],"sense":[{"gloss":"glass (drinking vessel)","pos":["n"]},{"gloss":"glass (material)","pos":["n"],"x":["ガラス"]},{"gloss":"glasses (eyewear)","pos":["n"]}]},"sdata":[{"j":"↑空↑↓から↓の|グラス|がいくつか↑欲↑↓ほ↓しい。","e":"I want a few empty glasses."},{"j":"↑怪↑↓あや↓しげな↑手↑↓て↓つきで↑彼女↑↓かのじょ↓は|グラス|を↑運↑↓はこ↓んできた。","e":"She fumbled with the glasses as she brought them in."},{"j":"わたし|グラス|を↑持↑↓も↓ってくるわ。","e":"I'll get some glasses."},{"j":"ボトルですか？|グラス|ですか？","e":"Bottle or glass?"},{"j":"どちらの|グラス|をとってもよい。","e":"You may take either of the glasses."},{"j":"テーブルの↑縁↑↓えにし↓に|グラス|を↑置↑↓お↓かないで↑下↑↓くだ↓さい。","e":"Don't put the glass near the edge of the table."},{"j":"チップが|グラス|↑一↑↓ひと↓つの↑中↑↓なか↓の１０セントであれば、ウェイトレスは↑次↑↓つぎ↓の↑客↑↓きゃく↓に↑備↑↓そな↓えて↑急↑↓いそ↓いでテーブルを↑片付↑↓かたづ↓けようとして|グラス|を↑持↑↓も↓ち↑上↑↓あ↓げ、↑水↑↓みず↓がこぼれだし、↑事↑↓こと↓はおしまいということになろう。","e":"If the tip was a dime in one glass, the waitress, in her haste to get the table ready for the next customer, would pick up the glass, the water would spill out, and that would be the end of it."},{"j":"その↑後↑↓ご↓、カードを↑引↑↓ひ↓き↑抜↑↓ぬ↓いた。↑空気↑↓くうき↓はまったく↑入↑↓はい↓っていないので↑水↑↓みず↓は↑漏↑↓も↓れない。|グラス|の↑縁↑↓えにし↓はぴったりテーブルに↑接↑↓せっ↓しているから。","e":"Then I slipped out the card. No water leaks out because no air can come in; the rim is too close to the table for that."},{"j":"そのワイン|グラス|の↑取↑↓と↓り↑扱↑↓あつか↓いには↑気↑↓き↓を↑付↑↓つ↓けてね。","e":"You must be careful with the wine glass."},{"j":"その|グラス|は↑空↑↓から↓だった。","e":"I found the glass empty."}]}