{"data":{"r_ele":[{"r":"パーク","p":true}],"sense":[{"gloss":"park (public, amusement, etc.)","pos":["n"]},{"gloss":"parking","pos":["n"]}]},"sdata":[{"j":"↑我々↑↓われわれ↓はその↑夜↑↓よる↓、ロードサイド|パーク|で↑寝↑↓ね↓た。","e":"We bedded down at the roadside park for the night."},{"j":"↑映画↑↓えいが↓『ジュラシック・|パーク|』の↑恐竜↑↓きょうりゅう↓は↑本物↑↓ほんもの↓そっくりだ。","e":"The dinosaurs in the film \"Jurassic Park\" were true to life."},{"j":"ローザ・|パーク|スは↑逮捕↑↓たいほ↓され、モントゴメリー↑市↑↓し↓の↑黒人↑↓こくじん↓たちはショックを↑受↑↓う↓け↑激怒↑↓げきど↓した。","e":"Rosa Parks was arrested, and the black community of Montgomery was shocked and angry."},{"j":"|パーク|↑通↑↓どお↓りにどうやって↑行↑↓い↓くのか↑教↑↓おし↓えていただけますか。","e":"Could you tell me how to get to Park Street?"},{"j":"どのようにしてハイド|パーク|へ↑行↑↓い↓ったらいいか↑教↑↓おし↓えてくれませんか。","e":"Can you tell me how to get to Hyde Park?"},{"j":"セントラル|パーク|はどちらへ↑行↑↓い↓くのですか。","e":"Which way is Central Park?"},{"j":"セントラル|パーク|は、↑私↑↓わたし↓の↑働↑↓はたら↓いている↑所↑↓ところ↓の↑近↑↓ちか↓くにあります。","e":"Central Park is near where I work."},{"j":"すみませんが、セントラル|パーク|にはどうやって↑行↑↓い↓ったらいいか↑教↑↓おし↓えていただけませんか。","e":"Excuse me, but could you tell me how to get to Central Park?"},{"j":"サファリ|パーク|にいらっしゃるなら５↑番↑↓ばん↓のバスです。","e":"If you are going to the safari park, take the No.5 bus."},{"j":"このバスは、|パーク|リッジ↑行↑↓い↓きですか。","e":"Is this the bus for Park Ridge?"}]}