{"data":{"r_ele":[{"r":"リストラ","p":true}],"sense":[{"gloss":"(corporate) restructuring","pos":["n"],"m":["abbr"],"x":["リストラクチュアリング・2"]},{"gloss":"downsizing, laying off (workers)","pos":["n","vs","vt"]}]},"sdata":[{"j":"↑会議↑↓かいぎ↓の↑席↑↓せき↓で↑常務↑↓じょうむ↓は、↑開口一番↑↓かいこういちばん↓↑何↑↓なに↓を↑言↑↓い↓ったと↑思↑↓おも↓う。↑大↑↓だい↓↑規模↑↓きぼ↓な|リストラ|↑計画↑↓けいかく↓を↑発表↑↓はっぴょう↓したんだよな。","e":"Guess what the managing director started off the meeting by saying. The first thing out of his mouth was an announcement of some major restructuring."},{"j":"|リストラ|された↑彼↑↓かれ↓は↑心機一転↑↓しんきいってん↓、↑自宅↑↓じたく↓を↑拠点↑↓きょてん↓にＳＯＨＯビジネスを↑始↑↓はじ↓めた。","e":"After getting downsized he started off on a clean slate and started a business working out of a home office."},{"j":"↑営業↑↓えいぎょう↓マンだって、|リストラ|↑予備↑↓よび↓↑軍↑↓ぐん↓に↑配属↑↓はいぞく↓されないように↑必死↑↓ひっし↓な↑訳↑↓わけ↓です。","e":"After all, even salesmen are desperate to avoid being targeted for downsizing."},{"j":"コストダウンもできない↑生↑↓なま↓ぬるい|リストラ|がJAL↑再建↑↓さいけん↓を↑危↑↓あや↓うくする。","e":"Half-hearted cutbacks that can't save money leave JAL's rehabilitation in doubt."},{"j":"トムは|リストラ|された。","e":"Tom was made redundant."}]}