{"data":{"k_ele":[{"e":"万世","p":true}],"r_ele":[{"r":"ばんせい","p":true}],"sense":[{"gloss":"all ages, eternity","pos":["n","adv"]}]},"kdata":{"万":{"on":["マン","バン"],"kun":["よろず"],"jlpt":5,"meanings":["10 000","ten thousand","10,000"],"freq":375,"comp":[["丆","𠃌"]],"d":["方","栃","杤","厉"],"s":"方","t":37},"世":{"on":["セイ","セ","ソウ"],"kun":["よ"],"jlpt":4,"meanings":["generation","world","society","public"],"freq":135,"comp":[["廿","𠃊"]],"d":["笹","貰","泄","枻","紲","伳","呭","屜","枼","詍","跇","迣"],"t":182}},"sdata":[]}