{"data":{"k_ele":[{"e":"予定表","p":true}],"r_ele":[{"r":"よていひょう","p":true}],"sense":[{"gloss":"schedule, program, programme, itinerary","pos":["n"]}]},"kdata":{"予":{"on":["ヨ","シャ"],"kun":["あらかじ.め"],"jlpt":3,"meanings":["beforehand","previous","myself","I"],"freq":180,"comp":[["マ","丁"]],"d":["野","預","序","矛","抒","豫","舒","杼","妤","𥝱","芧","伃","忬","紓","魣","𩿎"],"s":"矛","t":96},"定":{"on":["テイ","ジョウ"],"kun":["さだ.める","さだ.まる","さだ.か"],"jlpt":3,"meanings":["decide","determine","fix","establish"],"freq":48,"comp":[["宀","疋"]],"d":["錠","淀","綻","掟","碇","諚","聢","埞","椗","靛"],"s":"足","t":645},"表":{"on":["ヒョウ"],"kun":["おもて","-おもて","あらわ.す","あらわ.れる","あら.わす"],"jlpt":3,"meanings":["surface","table","chart","diagram"],"freq":77,"comp":[["𧘇","龶"]],"d":["俵","錶","裱"],"s":"麦","t":760}},"sdata":[{"j":"|↑予定↑↓よてい↓↑表|↑↓ひょう↓を↑見↑↓み↓ましょう。","e":"I'll check my schedule."}]}