{"data":{"k_ele":[{"e":"以来","p":true}],"r_ele":[{"r":"いらい","p":true}],"sense":[{"gloss":"since, henceforth","pos":["n","adv"]}]},"kdata":{"以":{"on":["イ"],"kun":["もっ.て"],"jlpt":4,"meanings":["by","by means of","because","in view of","compared with"],"freq":126,"comp":[["丶","人","𠄌"]],"d":["似","苡","姒","鉯"],"t":188},"来":{"on":["ライ","タイ"],"kun":["く.る","きた.る","きた.す","き.たす","き.たる","き","こ"],"jlpt":5,"meanings":["come","due","next","cause","become"],"freq":102,"comp":[["未","丷"]],"d":["莱","𪎌"],"t":525}},"sdata":[{"j":"↑我々↑↓われわれ↓は↑衣服↑↓いふく↓を↑着↑↓き↓るようになって|↑以来|↑↓いらい↓、お↑互↑↓たが↓いが↑分↑↓わ↓からなくなった。","e":"Ever since we've been wearing clothes, we haven't known one another."},{"j":"↑我々↑↓われわれ↓はここに↑７月|↑↓しちがつ↓↑以来|↑↓いらい↓↑住↑↓す↓んでいる。","e":"We've been living here since July."},{"j":"↑科学↑↓かがく↓↑的↑↓てき↓↑知識↑↓ちしき↓は１６↑世紀|↑↓せいき↓↑以来|↑↓いらい↓↑大↑↓おお↓いに↑進歩↑↓しんぽ↓してきた。","e":"Scientific knowledge has greatly advanced since the 16th century."},{"j":"|↑以来|↑↓いらい↓ずっと↑友人↑↓ゆうじん↓です。","e":"We've been friends ever since."},{"j":"わが↑社↑↓しゃ↓も↑設立|↑↓せつりつ↓↑以来|↑↓いらい↓よく↑伸↑↓の↓びたもんだ。","e":"Our company has come a long way since it was set up."},{"j":"ロンドンへいって|↑以来|↑↓いらい↓、↑彼女↑↓かのじょ↓は↑電話↑↓でんわ↓をかけてきていない。","e":"She hasn't phoned since she went to London."},{"j":"もうそれ|↑以来|↑↓いらい↓↑彼↑↓かれ↓に↑会↑↓あ↓うことはなかった。","e":"I saw him no more."},{"j":"マリガンは１４↑ヶ月↑↓かげつ↓↑前↑↓まえ↓に↑逆転↑↓ぎゃくてん↓で↑王座↑↓おうざ↓を↑奪取↑↓だっしゅ↓して|↑以来|↑↓いらい↓、まったくの↑負↑↓ま↓けしらずです。","e":"Mulligan has been riding high since he seized the crown in a come-from-behind victory 14 months ago."},{"j":"トムとスーはお↑互↑↓たが↓いに１９８５↑年|↑↓ねん↓↑以来|↑↓いらい↓の↑知↑↓し↓り↑合↑↓あ↓いだ。","e":"Tom and Sue have known each other since 1985."},{"j":"ダイエットして|↑以来|↑↓いらい↓、↑彼女↑↓かのじょ↓はずいぶん↑体重↑↓たいじゅう↓が↑減↑↓へ↓った。","e":"She's lost a lot of weight since she went on a diet."},{"j":"それ|↑以来|↑↓いらい↓↑彼↑↓かれ↓らは↑愛↑↓あい↓し↑合↑↓あ↓うようになった。","e":"From that time on, they came to love each other."},{"j":"それ|↑以来|↑↓いらい↓↑彼↑↓かれ↓らの↑消息↑↓しょうそく↓は↑不明↑↓ふめい↓だ。","e":"They have never been heard of since."},{"j":"それ|↑以来|↑↓いらい↓↑彼↑↓かれ↓は↑全力↑↓ぜんりょく↓をあげて↑自分↑↓じぶん↓の↑仕事↑↓しごと↓に↑没頭↑↓ぼっとう↓した。","e":"Since then he has put his soul into his work."},{"j":"それ|↑以来|↑↓いらい↓↑彼↑↓かれ↓はだらしない↑生活↑↓せいかつ↓をしてきた。","e":"He has led a loose life since then."},{"j":"それ|↑以来|↑↓いらい↓↑彼↑↓かれ↓のうわさは↑聞↑↓き↓いていない。","e":"He has never been heard of since."},{"j":"それ|↑以来|↑↓いらい↓↑彼↑↓かれ↓から↑一↑↓いち↓↑度↑↓ど↓も↑便↑↓たよ↓りがない。","e":"We have never heard from him since."},{"j":"それ|↑以来|↑↓いらい↓、↑彼↑↓かれ↓からは↑何↑↓なん↓の↑便↑↓たよ↓りもありません。","e":"I have never heard from him since."},{"j":"それ|↑以来|↑↓いらい↓↑我々↑↓われわれ↓の↑勢力↑↓せいりょく↓↑範囲↑↓はんい↓は↑拡大↑↓かくだい↓してきた。","e":"Our sphere of influence has expanded so much since then."},{"j":"それ|↑以来|↑↓いらい↓ずっと↑私↑↓わたし↓たちは↑友達↑↓ともだち↓である。","e":"We have been friends ever since."},{"j":"それ|↑以来|↑↓いらい↓こちらに↑来↑↓きた↓られたことがありますか。","e":"Have you been here since?"},{"j":"それ|↑以来|↑↓いらい↓ずっととてもよい↑天気↑↓てんき↓が↑続↑↓つづ↓いています。","e":"It has been very fine since then."},{"j":"それ|↑以来|↑↓いらい↓↑３↑↓さん↓↑年↑↓ねん↓が↑経過↑↓けいか↓した。","e":"Three years have passed since then."},{"j":"それ|↑以来|↑↓いらい↓、↑彼女↑↓かのじょ↓は↑母親↑↓ははおや↓を↑尊敬↑↓そんけい↓することが↑出来↑↓でき↓なかった。","e":"Since then she couldn't look up to her mother."},{"j":"それ|↑以来|↑↓いらい↓、↑彼↑↓かれ↓の↑消息↑↓しょうそく↓を↑聞↑↓き↓いていない。","e":"He has not been heard of since."},{"j":"その↑時|↑↓とき↓↑以来|↑↓いらい↓↑私↑↓わたし↓は↑彼女↑↓かのじょ↓に↑会↑↓あ↓っていない。","e":"I haven't seen her since then."},{"j":"その↑日|↑↓ひ↓↑以来|↑↓いらい↓↑彼↑↓かれ↓はその↑少年↑↓しょうねん↓と↑暮↑↓く↓らすことになった。","e":"From that day forth he lived with the boy."},{"j":"その↑時|↑↓とき↓↑以来|↑↓いらい↓↑彼女↑↓かのじょ↓はずっと↑彼↑↓かれ↓に↑仕↑↓つか↓えた。","e":"From that time on, she always waited on him."},{"j":"↑私↑↓わたし↓はそれ|↑以来|↑↓いらい↓↑彼↑↓かれ↓の↑消息↑↓しょうそく↓は↑聞↑↓き↓いていない。","e":"I haven't heard from him since then."},{"j":"その↑時|↑↓とき↓↑以来|↑↓いらい↓、↑彼↑↓かれ↓から↑何↑↓なん↓の↑便↑↓たよ↓りもない。","e":"I haven't heard from him since then."},{"j":"その↑時|↑↓とき↓↑以来|↑↓いらい↓↑私↑↓わたし↓↑達↑↓たち↓は↑彼↑↓かれ↓にあっていない。","e":"Since that time we have not seen him."},{"j":"その↑時|↑↓とき↓↑以来|↑↓いらい↓、↑彼↑↓かれ↓は↑自分↑↓じぶん↓を↑虐待↑↓ぎゃくたい↓するものに↑対↑↓たい↓して↑尽↑↓つ↓きる↑事↑↓こと↓のない↑憎↑↓にく↓しみを↑感↑↓かん↓じるようになった。","e":"From that moment on, he felt undying hatred for his oppressors."},{"j":"その↑協会↑↓きょうかい↓は↑設立|↑↓せつりつ↓↑以来|↑↓いらい↓、↑素人↑↓しろうと↓の↑入会↑↓にゅうかい↓を↑断↑↓ことわ↓ってきた。","e":"The association has excluded amateurs ever since its foundation."},{"j":"そのとき|↑以来|↑↓いらい↓↑彼↑↓かれ↓と↑知↑↓し↓り↑合↑↓あ↓いになった。","e":"I've got acquainted with him since then."},{"j":"ジョンは１９７６↑年|↑↓ねん↓↑以来|↑↓いらい↓の↑知↑↓し↓り↑合↑↓あ↓いです。","e":"I have known John since 1976."},{"j":"ジョンとメアリーは１９７６↑年|↑↓ねん↓↑以来|↑↓いらい↓の↑知↑↓し↓り↑合↑↓あ↓いです。","e":"John and Mary have known each other since 1976."},{"j":"シェリーは↑僕↑↓ぼく↓が↑最後↑↓さいご↓にあって|↑以来|↑↓いらい↓↑本当↑↓ほんとう↓に↑太↑↓ふと↓ったなぁ。","e":"Shelly's really filled out since the last time I saw her."},{"j":"ジェインが↑東京↑↓とうきょう↓に↑引↑↓ひ↓っ↑越↑↓こ↓して|↑以来|↑↓いらい↓、↑連絡↑↓れんらく↓がないんだ。","e":"I haven't heard from Jane since she moved to Tokyo."},{"j":"この↑前↑↓ぜん↓↑手紙↑↓てがみ↓を↑書↑↓か↓いた↑時|↑↓とき↓↑以来|↑↓いらい↓↑別↑↓べつ↓に↑新↑↓あたら↓しい↑事↑↓こと↓は↑何↑↓なに↓も↑起↑↓お↓こっていない。","e":"There is nothing new transpired since I wrote you last."},{"j":"この↑前↑↓ぜん↓あなたにお↑会↑↓あ↓いして|↑以来|↑↓いらい↓、かなり↑進歩↑↓しんぽ↓されたようですね。","e":"You seem to have made considerable progress since I saw you last."},{"j":"このあたりは↑私↑↓わたし↓がここにきて|↑以来|↑↓いらい↓↑建↑↓た↓て↑込↑↓こ↓んできた。","e":"The area has been built up since I came here."}]}