{"data":{"k_ele":[{"e":"使い込む","p":true},{"e":"使いこむ"},{"e":"遣い込む","i":["oK"]}],"r_ele":[{"r":"つかいこむ","p":true}],"sense":[{"gloss":"to embezzle, to misappropriate, to peculate","pos":["v5m","vt"]},{"gloss":"to accustom oneself to using, to use for a long time","pos":["v5m","vt"]}]},"kdata":{"使":{"on":["シ"],"kun":["つか.う","つか.い","-つか.い","-づか.い"],"jlpt":4,"meanings":["use","send on a mission","order","messenger","envoy","ambassador","cause"],"freq":219,"comp":[["吏","亻"]],"s":"便","t":597},"込":{"kun":["-こ.む","こ.む","こ.み","-こ.み","こ.める"],"jlpt":3,"meanings":["crowded","mixture","in bulk","included","(kokuji)"],"freq":675,"comp":[["辶","入"]],"t":277}},"sdata":[]}