{"data":{"k_ele":[{"e":"官庁","p":true}],"r_ele":[{"r":"かんちょう","p":true}],"sense":[{"gloss":"government office, government agency, authorities","pos":["n"]}]},"kdata":{"官":{"on":["カン"],"jlpt":3,"meanings":["organ","bureaucrat","the government","organ"],"freq":230,"comp":[["宀","㠯"]],"d":["管","館","菅","棺","舘","綰","琯","倌","痯","輨","逭","錧","涫"],"s":"宮","t":643},"庁":{"on":["チョウ","テイ"],"kun":["やくしょ"],"jlpt":2,"meanings":["government office"],"freq":793,"comp":[["广","丁"]],"t":219}},"sdata":[{"j":"どの|↑官庁|↑↓かんちょう↓もお↑役所↑↓やくしょ↓↑主義↑↓しゅぎ↓にはまり↑込↑↓こ↓まないで、↑仕事↑↓しごと↓のスピードアップをはかるという↑点↑↓てん↓において↑問題↑↓もんだい↓があるようだ。","e":"Every government office seems to have problems in expediting matters without entanglement in its red tape system."},{"j":"↑彼↑↓かれ↓は|↑官庁|↑↓かんちょう↓で↑相当↑↓そうとう↓な↑職↑↓しょく↓についている。","e":"He has a good position in a government office."}]}