{"data":{"k_ele":[{"e":"度胸","p":true}],"r_ele":[{"r":"どきょう","p":true}],"sense":[{"gloss":"courage, bravery, pluck, nerve, grit, guts","pos":["n"]}]},"kdata":{"度":{"on":["ド","ト","タク"],"kun":["たび","-た.い"],"jlpt":4,"meanings":["degrees","occurrence","time","counter for occurrences","consider","attitude"],"freq":110,"comp":[["广","廿","又"]],"d":["渡","鍍","踱"],"s":"席","t":856},"胸":{"on":["キョウ"],"kun":["むね","むな-"],"jlpt":2,"meanings":["bosom","breast","chest","heart","feelings"],"freq":1144,"comp":[["匈","月"]],"t":1155}},"sdata":[{"j":"いい|↑度胸|↑↓どきょう↓してるな。","e":"You have a lot of nerve."},{"j":"あいつの|↑度胸|↑↓どきょう↓を↑試↑↓ため↓してみよう。","e":"I'll put his courage to the test."},{"j":"↑今度↑↓こんど↓はそれを↑持↑↓も↓ち↑上↑↓あ↓げる|↑度胸|↑↓どきょう↓はとうていないであろう。","e":"She just can't have the nerve to lift it up now!"},{"j":"↑男↑↓おとこ↓は|↑度胸|↑↓どきょう↓、↑女↑↓おんな↓は↑愛敬↑↓あいきょう↓。","e":"Man is judged by his courage, woman by her charm."},{"j":"|↑度胸|↑↓どきょう↓があるな。","e":"You have got a lot of nerve."},{"j":"|↑度胸|↑↓どきょう↓のない↑自分↑↓じぶん↓に、↑我↑↓われ↓ながらひどく↑腹↑↓はら↓が↑立↑↓た↓った。","e":"I was very angry with myself for my lack of courage."},{"j":"↑彼↑↓かれ↓に↑一↑↓いち↓↑人↑↓にん↓で↑会↑↓あ↓うとは↑彼女↑↓かのじょ↓もいい|↑度胸|↑↓どきょう↓だ。","e":"She must have some nerve to go and meet him by herself."},{"j":"↑彼↑↓かれ↓は|↑度胸|↑↓どきょう↓を↑据↑↓す↓えて↑外人↑↓がいじん↓に↑話↑↓はな↓し↑掛↑↓か↓けた。","e":"He mustered up his courage to talk to a foreigner."},{"j":"なによ！↑出来↑↓でき↓ないの？この|↑度胸|↑↓どきょう↓なし！↑腰抜↑↓こしぬ↓けッ！","e":"What? You can't do it? You coward! Chicken!"},{"j":"ケンはもう↑一度↑↓いちど↓やってみる|↑度胸|↑↓どきょう↓がなかった。","e":"Ken didn't have the nerve to try it again."},{"j":"トムだけがそういったことをする|↑度胸|↑↓どきょう↓があるだろう。","e":"Only Tom would have the guts to do that kind of thing."},{"j":"|↑度胸|↑↓どきょう↓が↑足↑↓た↓りないぞ。","e":"You don't have the guts."},{"j":"↑彼女↑↓かのじょ↓に↑張↑↓は↓り↑合↑↓あ↓おうとは、いい|↑度胸|↑↓どきょう↓ね。","e":"To pick a fight with her, that's courageous."},{"j":"トムは|↑度胸|↑↓どきょう↓がない。","e":"Tom lacks courage."},{"j":"このワタクシをさらりと↑無視↑↓むし↓するとは↑良↑↓よ↓い|↑度胸|↑↓どきょう↓ですわね。","e":"You must have some nerve to ignore me."},{"j":"↑僕↑↓ぼく↓から↑逃↑↓に↓げるなんていい|↑度胸|↑↓どきょう↓じゃないか。","e":"You've got some nerve running away from me, haven't you?"},{"j":"↑手↑↓て↓ェ↑出↑↓だ↓すたぁ、いい|↑度胸|↑↓どきょう↓だ。","e":"It takes real guts to start a fight."}]}