{"data":{"k_ele":[{"e":"強弁","p":true}],"r_ele":[{"r":"きょうべん","p":true}],"sense":[{"gloss":"insisting (unreasonably), obstinate insistence","pos":["n","vs","vt"]}]},"kdata":{"強":{"on":["キョウ","ゴウ"],"kun":["つよ.い","つよ.まる","つよ.める","し.いる","こわ.い"],"jlpt":4,"meanings":["strong"],"freq":112,"comp":[["弘","虫"]],"t":1274},"弁":{"on":["ベン","ヘン"],"kun":["かんむり","わきま.える","わ.ける","はなびら","あらそ.う"],"jlpt":1,"meanings":["speech","valve","petal","braid","dialect","discrimination","dispose of","distinguish","conical cap"],"freq":619,"comp":[["厶","廾"]],"d":["峅","昪","匥","拚","閞","鴘"],"t":234}},"sdata":[]}