{"data":{"k_ele":[{"e":"扇動","p":true},{"e":"煽動"}],"r_ele":[{"r":"せんどう","p":true}],"sense":[{"gloss":"incitement, sedition, agitation, abetting","pos":["n","vs","vt"]}]},"kdata":{"扇":{"on":["セン"],"kun":["おうぎ"],"jlpt":1,"meanings":["fan","folding fan"],"freq":1805,"comp":[["羽","戶"]],"d":["煽","騸","傓","謆"],"t":1076},"動":{"on":["ドウ"],"kun":["うご.く","うご.かす"],"jlpt":4,"meanings":["move","motion","change","confusion","shift","shake"],"freq":73,"comp":[["重","力"]],"d":["働","勲","慟"],"t":1240}},"sdata":[{"j":"↑学生↑↓がくせい↓↑達↑↓たち↓は|↑扇動|↑↓せんどう↓↑者↑↓しゃ↓のアピールに↑動↑↓うご↓かされた。","e":"The students were animated by the agitator's appeal."},{"j":"その|↑扇動|↑↓せんどう↓↑家↑↓か↓は↑些細↑↓ささい↓なことを↑大袈裟↑↓おおげさ↓に↑表現↑↓ひょうげん↓する↑傾向↑↓けいこう↓がある。","e":"The agitator is inclined to exaggerate trivial matters."},{"j":"↑土地↑↓とち↓の↑人々↑↓ひとびと↓を|↑扇動|↑↓せんどう↓するためにスパイを↑送↑↓おく↓り↑込↑↓こ↓んだ。","e":"They sent agents to agitate the local people."},{"j":"↑暴動↑↓ぼうどう↓は↑彼↑↓かれ↓の|↑扇動|↑↓せんどう↓によって↑起↑↓お↓こった。","e":"He instigated the riot."}]}