{"data":{"k_ele":[{"e":"救急医療","p":true}],"r_ele":[{"r":"きゅうきゅういりょう","p":true}],"sense":[{"gloss":"emergency medicine","pos":["n"]}]},"kdata":{"救":{"on":["キュウ"],"kun":["すく.う"],"jlpt":1,"meanings":["salvation","save","help","rescue","reclaim"],"freq":799,"comp":[["攵","求"]],"t":1300},"急":{"on":["キュウ"],"kun":["いそ.ぐ","いそ.ぎ","せ.く"],"jlpt":4,"meanings":["hurry","emergency","sudden","steep"],"freq":309,"comp":[["刍","心"]],"t":865},"医":{"on":["イ"],"kun":["い.やす","い.する","くすし"],"jlpt":4,"meanings":["doctor","medicine"],"freq":437,"comp":[["匚","矢"]],"d":["悘","殹"],"t":453},"療":{"on":["リョウ"],"jlpt":2,"meanings":["heal","cure"],"freq":600,"comp":[["疒","尞"]],"t":2186}},"sdata":[{"j":"↑事故↑↓じこ↓があるとすぐに|↑救急↑↓きゅうきゅう↓↑医療|↑↓いりょう↓↑隊↑↓たい↓が↑到着↑↓とうちゃく↓する。","e":"Medical help arrives promptly after an accident."}]}