{"data":{"k_ele":[{"e":"構いません","p":true}],"r_ele":[{"r":"かまいません","p":true}],"sense":[{"gloss":"no problem, it doesn't matter","pos":["exp"]}]},"kdata":{"構":{"on":["コウ"],"kun":["かま.える","かま.う"],"jlpt":3,"meanings":["build / posture","posture","build","pretend"],"freq":316,"comp":[["冓","木"]],"s":"横","t":1881}},"sdata":[{"j":"ちっとも|↑構↑↓かま↓いません|よ。","e":"I don't care."},{"j":"↑一↑↓いっ↓↑杯↑↓ぱい↓↑頂↑↓いただ↓いても|↑構↑↓かま↓いません|。","e":"I wouldn't mind a drink."},{"j":"↑帰↑↓かえ↓りたいなら↑帰↑↓かえ↓っても|↑構↑↓かま↓いません|。","e":"You may go home if you want to."},{"j":"どっちでも|↑構↑↓かま↓いません|。","e":"It doesn't matter."},{"j":"どちらでも↑好↑↓す↓きな↑道↑↓みち↓を↑行↑↓い↓っていただいて|↑構↑↓かま↓いません|。","e":"You can take whichever road you like."},{"j":"↑本↑↓ほん↓は↑持↑↓も↓っていっても|↑構↑↓かま↓いません|よ。","e":"You may take the book."},{"j":"「たばこを↑吸↑↓す↓ってもかまいませんか」「ええ、↑少↑↓すこ↓しも|↑構↑↓かま↓いません|よ」","e":"Do you mind if I smoke? \"No, I don't mind at all.\""},{"j":"↑好↑↓す↓きなだけお↑話↑↓はな↓しいただいて|↑構↑↓かま↓いません|。","e":"You may talk as much as you like."},{"j":"↑私↑↓わたし↓はそれで↑一向↑↓いっこう↓に|↑構↑↓かま↓いません|。","e":"That's just fine with me."},{"j":"↑私↑↓わたし↓はどうなっても|↑構↑↓かま↓いません|。","e":"I don't care what will become of me."},{"j":"↑私↑↓わたし↓は|↑構↑↓かま↓いません|よ。","e":"I don't mind."},{"j":"いつでも↑好↑↓す↓きな↑時↑↓とき↓に↑帰↑↓かえ↓って|↑構↑↓かま↓いません|。","e":"You are free to leave any time you wish."},{"j":"↑全↑↓まった↓く|↑構↑↓かま↓いません|。","e":"It's quite all right."},{"j":"↑賃料↑↓ちんりょう↓が↑手頃↑↓てごろ↓なら、どんなマンションでも|↑構↑↓かま↓いません|。","e":"Any apartment will do as long as the rent is reasonable."},{"j":"↑庭↑↓にわ↓を↑通↑↓とお↓っても|↑構↑↓かま↓いません|か。","e":"Do you mind if we cross your garden?"},{"j":"↑内線↑↓ないせん↓２１４に↑出↑↓で↓る↑人↑↓ひと↓なら↑誰↑↓だれ↓でも|↑構↑↓かま↓いません|。","e":"I'll speak to anyone at extension 214."},{"j":"↑返事↑↓へんじ↓はしなくても|↑構↑↓かま↓いません|よ。","e":"It doesn't matter whether you answer or not."},{"j":"↑夕食↑↓ゆうしょく↓はどこでも|↑構↑↓かま↓いません|。お↑任↑↓まか↓せします。","e":"I don't care where we eat dinner. It's entirely up to you."},{"j":"|↑構↑↓かま↓いません|よ。いつもの↑夜↑↓よる↓↑酒↑↓しゅ↓です。たまにはパートナーがいるのもいいものでしょう。","e":"I'm not bothered. It's just my usual nightcap. Having someone to drink with on occasion might be nice."},{"j":"テレビをつけても|↑構↑↓かま↓いません|か。","e":"Do you mind my turning on the TV?"},{"j":"ちっとも|↑構↑↓かま↓いません|よ。","e":"It doesn't matter to me one bit."},{"j":"どうやって↑訳↑↓やく↓したらよいか↑判↑↓わか↓らない↑文章↑↓ぶんしょう↓を↑追加↑↓ついか↓しても|↑構↑↓かま↓いません|。↑他↑↓ほか↓の↑誰↑↓だれ↓かが↑知↑↓し↓っているかもしれませんので。","e":"You can add sentences that you do not know how to translate. Perhaps someone else will know."},{"j":"↑決↑↓き↓めるのは↑今↑↓いま↓でなくて|↑構↑↓かま↓いません|よ。","e":"You don't need to make a decision now."},{"j":"↑一↑↓ひと↓つ↑一↑↓ひと↓つの↑単語↑↓たんご↓や↑表現↑↓ひょうげん↓をテキストから↑持↑↓も↓ってくるのは|↑構↑↓かま↓いません|が、↑文章↑↓ぶんしょう↓↑全部↑↓ぜんぶ↓はだめです。","e":"You can take single words or expressions from the text, but not complete sentences."},{"j":"↑本↑↓ほん↓は↑持↑↓も↓っていっても|↑構↑↓かま↓いません|よ。","e":"It's OK with me if you take that book."},{"j":"↑本↑↓ほん↓は↑持↑↓も↓っていっても|↑構↑↓かま↓いません|よ。","e":"It doesn't bother me if you take that book."},{"j":"↑本↑↓ほん↓は↑持↑↓も↓っていっても|↑構↑↓かま↓いません|よ。","e":"It doesn't matter to me if you take that book."},{"j":"「お↑宅↑↓たく↓にお↑邪魔↑↓じゃま↓してもよろしいですか」「いつでも|↑構↑↓かま↓いません|よ」","e":"May I come over to your house? \"Anytime you want.\""},{"j":"お↑好↑↓す↓きなだけ↑時間↑↓じかん↓をとっても|↑構↑↓かま↓いません|よ。","e":"Take all the time you want."},{"j":"↑次↑↓つぎ↓の↑授業↑↓じゅぎょう↓までに、↑歌詞↑↓かし↓を↑文字↑↓もじ↓に↑起↑↓お↓こしてきてください。どんな↑歌手↑↓かしゅ↓の↑歌↑↓うた↓でも↑英語↑↓えいご↓であれば|↑構↑↓かま↓いません|。","e":"For the next class, I want you to transcribe the lyrics from a song by any singer as long as it's in English."},{"j":"ソファーに↑横↑↓よこ↓になっても|↑構↑↓かま↓いません|か。","e":"Do you mind if I lay down on the sofa?"},{"j":"それで|↑構↑↓かま↓いません|か？","e":"Are you cool with that?"},{"j":"↑座↑↓すわ↓っても|↑構↑↓かま↓いません|か？","e":"Do you mind if I sit down?"},{"j":"↑明日↑↓あした↓の↑午後↑↓ごご↓でしたら、いつ↑来↑↓き↓てもらっても|↑構↑↓かま↓いません|よ。","e":"You may come at any time tomorrow afternoon."},{"j":"いつでも|↑構↑↓かま↓いません|よ。","e":"Any time will suit me."},{"j":"↑窓↑↓まど↓を↑開↑↓あ↓けたいならどうぞ、|↑構↑↓かま↓いません|よ。","e":"You may go ahead and open the window if you want to."},{"j":"↑3↑↓みっ↓つ↑以上↑↓いじょう↓のものを↑列挙↑↓れっきょ↓するときは、↑A↑↓エイ↓, ↑B↑↓ビー↓, ↑C↑↓シー↓(,) ↑and↑↓アンド↓ ↑D↑↓ディー↓ というような↑言↑↓い↓い↑方↑↓かた↓をします。↑and↑↓アンド↓ の↑前↑↓まえ↓のコンマはあってもなくても|↑構↑↓かま↓いません|。","e":"If you are listing more than 3 items, use an expression like \"A, B, C, and D\", it doesn't matter if you exclude the comma before \"and\"."},{"j":"|↑構↑↓かま↓いません|よ。","e":"That's fine with me."},{"j":"↑私↑↓わたし↓はどうなっても|↑構↑↓かま↓いません|。","e":"I don't care what'll become of me."},{"j":"↑窓↑↓まど↓を↑開↑↓あ↓けても|↑構↑↓かま↓いません|よ。","e":"You may open the window."}]}