{"data":{"k_ele":[{"e":"水分","p":true}],"r_ele":[{"r":"すいぶん","p":true}],"sense":[{"gloss":"water, liquid, fluid, moisture, humidity, sap, juice","pos":["n"]}]},"kdata":{"水":{"on":["スイ"],"kun":["みず","みず-"],"jlpt":5,"meanings":["water"],"freq":223,"comp":[[]],"d":["永","泉","氷","尿","漿","沓","冰","潁","滎","閖","汞","盥","淼","砅","呇","囦","柡","氶","泴","洯","漦","澃","阥","頮","𣴎","㽷","漐","氽"],"s":"氷,永","t":150},"分":{"on":["ブン","フン","ブ"],"kun":["わ.ける","わ.け","わ.かれる","わ.かる","わ.かつ"],"jlpt":5,"meanings":["part","minute of time","segment","share","degree","one's lot","duty","understand","know","rate","1%","chances","shaku/100"],"freq":24,"comp":[["八","刀"]],"d":["紛","貧","雰","粉","盆","頒","扮","份","汾","芬","蚡","忿","邠","岔","坌","枌","氛","攽","盼","釁","瓫","玢","棼","鈖","鼢","吩","瓰","竕","肦","躮","酚","魵","麄","衯"],"s":"公","t":111}},"sdata":[{"j":"↑植物↑↓しょくぶつ↓は↑土壌↑↓どじょう↓から|↑水分|↑↓すいぶん↓をとる。","e":"Plants take in water from the soil."},{"j":"|↑水分|↑↓すいぶん↓は↑温↑↓あたた↓められると↑蒸発↑↓じょうはつ↓する。","e":"Water evaporates when it is heated."},{"j":"|↑水分|↑↓すいぶん↓をたくさん↑取↑↓と↓ってください。","e":"You should drink a lot of liquid."},{"j":"|↑水分|↑↓すいぶん↓を↑控↑↓ひか↓えてください。","e":"You should not drink a lot of liquid."},{"j":"|↑水分|↑↓すいぶん↓↑子↑↓こ↓は、２↑個↑↓こ↓の↑水素↑↓すいそ↓↑原子↑↓げんし↓と１↑個↑↓こ↓の↑酸素↑↓さんそ↓↑原子↑↓げんし↓からなる。","e":"A water molecule has two hydrogen atoms and one oxygen atom."},{"j":"↑空気↑↓くうき↓↑中↑↓ちゅう↓の|↑水分|↑↓すいぶん↓の↑内↑↓うち↓90%は↑海洋↑↓かいよう↓、↑湖沼↑↓こしょう↓、↑河川↑↓かせん↓から↑蒸発↑↓じょうはつ↓したものだ。","e":"Evaporation from oceans, lakes, and rivers creates 90% of the water in air."},{"j":"↑風邪↑↓かぜ↓を↑引↑↓ひ↓いたときはたくさん|↑水分|↑↓すいぶん↓を↑摂↑↓と↓らないといけない。","e":"When you have a cold, you should drink plenty of liquids."},{"j":"|↑水分|↑↓すいぶん↓↑子↑↓こ↓は↑一↑↓いち↓↑個↑↓こ↓の↑酸素↑↓さんそ↓↑原子↑↓げんし↓と↑二↑↓に↓↑個↑↓こ↓の↑水素↑↓すいそ↓↑原子↑↓げんし↓から↑出来↑↓でき↓ています。","e":"A molecule of water is made up of one oxygen and two hydrogen atoms."},{"j":"|↑水分|↑↓すいぶん↓と↑栄養↑↓えいよう↓しっかり↑摂↑↓と↓って、↑早↑↓はや↓く↑元気↑↓げんき↓になってね。","e":"Be sure to eat right and have lots of liquids. I hope you get well soon!"},{"j":"|↑水分|↑↓すいぶん↓と↑栄養↑↓えいよう↓しっかり↑摂↑↓と↓って、↑早↑↓はや↓く↑治↑↓なお↓してね。","e":"Make sure you drink plenty of fluids and nourish yourself and get better soon."}]}