{"data":{"k_ele":[{"e":"甘受","p":true}],"r_ele":[{"r":"かんじゅ","p":true}],"sense":[{"gloss":"submitting to (a demand, one's fate, etc.), putting up with, resigning oneself to, accepting (without complaint)","pos":["n","vs","vt"]}]},"kdata":{"甘":{"on":["カン"],"kun":["あま.い","あま.える","あま.やかす","うま.い"],"jlpt":2,"meanings":["sweet","coax","pamper","be content","sugary"],"freq":1248,"comp":[["一","廿"]],"d":["紺","某","柑","嵌","邯","甜","坩","酣","鉗","蚶","疳","咁","篏","泔","玵","拑","甞","苷"],"t":264},"受":{"on":["ジュ"],"kun":["う.ける","-う.け","う.かる"],"jlpt":3,"meanings":["accept","undergo","answer (phone)","take","get","catch","receive"],"freq":136,"comp":[["爫","冖","又"]],"d":["授","綬","閿","辤"],"s":"愛","t":620}},"sdata":[{"j":"↑君↑↓きみ↓はその↑結果↑↓けっか↓を|↑甘受|↑↓かんじゅ↓すべきだ。","e":"You should abide by the consequences."},{"j":"↑人↑↓ひと↓は↑運命↑↓うんめい↓を|↑甘受|↑↓かんじゅ↓せざるを↑得↑↓え↓ない。","e":"One can't quarrel with destiny."},{"j":"↑私↑↓わたし↓たちは↑自分↑↓じぶん↓が↑選択↑↓せんたく↓した↑結果↑↓けっか↓を|↑甘受|↑↓かんじゅ↓しなければならない。","e":"We have to live with the consequences of our choices."}]}