{"data":{"k_ele":[{"e":"福利","p":true}],"r_ele":[{"r":"ふくり","p":true}],"sense":[{"gloss":"welfare","pos":["n"]}]},"kdata":{"福":{"on":["フク"],"jlpt":3,"meanings":["blessing","fortune","luck","wealth"],"freq":467,"comp":[["畐","礻"]],"t":1757},"利":{"on":["リ"],"kun":["き.く"],"jlpt":3,"meanings":["profit","advantage","benefit"],"freq":203,"comp":[["刂","禾"]],"d":["梨","痢","莉","悧","鯏","俐","犁","唎","蜊","浰","鋓","峲","誗","鬁"],"t":448}},"sdata":[{"j":"↑国民↑↓こくみん↓の|↑福利|↑↓ふくり↓は↑政府↑↓せいふ↓の↑責任↑↓せきにん↓だ。","e":"The well being of the nation is the government's responsibility."},{"j":"↑彼↑↓かれ↓は↑社会↑↓しゃかい↓の|↑福利|↑↓ふくり↓のために↑貢献↑↓こうけん↓してくれた。","e":"He contributed to the good of the community."}]}