{"data":{"k_ele":[{"e":"称号","p":true}],"r_ele":[{"r":"しょうごう","p":true}],"sense":[{"gloss":"title, name, degree","pos":["n"]}]},"kdata":{"称":{"on":["ショウ"],"kun":["たた.える","とな.える","あ.げる","かな.う","はか.り","はか.る","ほめ.る"],"jlpt":1,"meanings":["appellation","praise","admire","name","title","fame"],"freq":985,"comp":[["尔","禾"]],"t":1137},"号":{"on":["ゴウ"],"kun":["さけ.ぶ","よびな"],"jlpt":3,"meanings":["nickname","number","item","title","pseudonym","name","call"],"freq":585,"comp":[["口","丂"]],"d":["號","鴞","枵"],"t":193}},"sdata":[{"j":"↑彼↑↓かれ↓はサーの|↑称号|↑↓しょうごう↓を↑持↑↓も↓っている。","e":"He bears the title of Sir."},{"j":"↑彼↑↓かれ↓は↑不名誉↑↓ふめいよ↓な|↑称号|↑↓しょうごう↓を↑得↑↓え↓た。","e":"He got a shameful title."},{"j":"フランクス↑陸軍↑↓りくぐん↓↑大将↑↓たいしょう↓がナイト↑爵位↑↓しゃくい↓の↑名誉|↑↓めいよ↓↑称号|↑↓しょうごう↓を↑授↑↓さず↓かりました。","e":"General Franks received an honorary knighthood."}]}