{"data":{"k_ele":[{"e":"緊密","p":true}],"r_ele":[{"r":"きんみつ","p":true}],"sense":[{"gloss":"rigour, rigor, closeness, compactness, tightly knit","pos":["adj-na","n"]}]},"kdata":{"緊":{"on":["キン"],"kun":["し.める","し.まる"],"jlpt":1,"meanings":["tense","solid","hard","reliable","tight"],"freq":677,"comp":[["臤","糸"]],"t":2032},"密":{"on":["ミツ"],"kun":["ひそ.か"],"jlpt":1,"meanings":["secrecy","density (pop)","minuteness","carefulness"],"freq":815,"comp":[["宓","山"]],"d":["樒","蔤"],"t":1262}},"sdata":[{"j":"↑今後↑↓こんご↓とも、↑貴社↑↓きしゃ↓と|↑緊密|↑↓きんみつ↓なおつきあいをいただけますよう↑希望↑↓きぼう↓しております。","e":"I hope that your future activities will expand our relationship with your firm."},{"j":"↑私↑↓わたし↓どもの↑関係↑↓かんけい↓がより|↑緊密|↑↓きんみつ↓になることを↑願↑↓ねが↓っております。","e":"We hope to establish a closer relationship between us."}]}