{"data":{"k_ele":[{"e":"装い","p":true},{"e":"粧い","i":["rK"]}],"r_ele":[{"r":"よそおい","p":true}],"sense":[{"gloss":"dress, outfit, equipment, makeup, adornment, guise, get-up","pos":["n"]}]},"kdata":{"装":{"on":["ソウ","ショウ"],"kun":["よそお.う","よそお.い"],"jlpt":2,"meanings":["attire","dress","pretend","disguise","profess"],"freq":657,"comp":[["壮","衣"]],"t":1599}},"sdata":[{"j":"↑彼↑↓かれ↓の↑服|装↑↓ふくそう↓い|つもださい。","e":"His clothes are always out of style."},{"j":"↑野山↑↓のやま↓は↑春↑↓はる↓の|↑装↑↓よそお↓い|だ。","e":"Hills and fields cloaked in spring colors."},{"j":"↑彼女↑↓かのじょ↓は↑平静↑↓へいせい↓を|↑装↑↓よそお↓い|、↑笑↑↓え↓みを↑絶↑↓た↓やさなかった。","e":"She put on a brave face and kept on smiling."}]}