{"data":{"k_ele":[{"e":"超能力","p":true}],"r_ele":[{"r":"ちょうのうりょく","p":true}],"sense":[{"gloss":"extra-sensory perception, ESP, psi, psychic ability","pos":["n"]},{"gloss":"psychokinesis, PK","pos":["n"]}]},"kdata":{"超":{"on":["チョウ"],"kun":["こ.える","こ.す"],"jlpt":2,"meanings":["transcend","super-","ultra-"],"freq":597,"comp":[["召","走"]],"t":1619},"能":{"on":["ノウ"],"kun":["よ.く","あた.う"],"jlpt":3,"meanings":["ability","talent","skill","capacity"],"freq":273,"comp":[["䏍","匕"]],"d":["態","熊","罷","褦"],"t":1156},"力":{"on":["リョク","リキ","リイ"],"kun":["ちから"],"jlpt":4,"meanings":["power","force","strength","strong","strain","bear up","exert"],"freq":62,"comp":[["丿","𠃌"]],"d":["動","協","加","男","勢","助","労","効","努","募","勤","功","勉","勧","幼","励","勇","勘","劣","劾","勅","勃","勁","勒","劫","勳","勱","劭","抛","勛","辦","勞","仂","釛","务","勸","勐","劼","勣","勵","劦","勍","劻","㔟","觔","另","勊","劬","飭","勔","勷","夯","艻","劵","勦","勠","朸","劜","劤","劥","劧","劯","劰","劶","劷","劸","劺","劽","勀","勄","勆","勈","勌","勏","勑","勖","勜","勡","勥","勨","勩","勪","勬","勴","勶","屴","忇","扐","氻","牞","竻","阞","𠢹","䏮","勉","勤"],"s":"刀,刃","t":17}},"sdata":[{"j":"トムは|↑超↑↓ちょう↓↑能力|↑↓のうりょく↓↑者↑↓しゃ↓なんだけど、メアリーは↑違↑↓ちが↓うよ。","e":"Tom is psychic, but Mary isn't."},{"j":"あいつの↑察↑↓さっ↓しの↑良↑↓よ↓さは|↑超↑↓ちょう↓↑能力|↑↓のうりょく↓と↑言↑↓い↓っていい。","e":"His guess was so good it could be called ESP."}]}